Workbook

Sheet Data
A1: Id | B1: Godzina rozpoczęcia | C1: Godzina ukończenia | D1: Adres e-mail | E1: Nazwa | F1: How old are you? | G1: What is your highest level of education? | H1: Is your educational background related to STEM (Science, Technology, Engineering, Mathematics)? | I1: What is your work arrangement? | J1: work arrangement ordinal | K1: In which industry/domain does your company operate (e.g., finance, game development, enterprise software)? | L1: What is the size of your company? | M1: How long have you been working in software development? | N1: What is your professional role? | O1: How big is your team? | P1: What types of projects do you most often work on? | Q1: Column | R1: How frequently do you experience interruptions in a typical workday? | S1: Frequency_ordinal | T1: What are the most common sources of interruptions in your work? | U1: What are these interruptions usually about? | V1: Who interrupts you most often at work? | W1: How much do interruptions disrupt your focus and workflow? (1 = not disruptive at all, 5 = very disruptive) | X1: How quickly do you switch to handling the new "interrupting " task? | Y1: Time_to_regain_focus_ordinal | Z1: On average, how long does it take you to regain full focus after an interruption? | AA1: Do you use any techniques to reduce interruptions (e.g., focus time, “do not disturb” status)? | AB1: What methods do you personally use to reduce or manage interruptions during your work? (max. 3) | AC1: How effective do you consider these methods to be? (1 = ineffective, 5 = very effective) | AD1: How do you rate your productivity in a typical workday? (1 = very low, 5 = very high) | AE1: How often do you feel that interruptions negatively affect the quality of your work? (1 = never, 5 - very often) | AF1: How satisfied are you with your job overall (job satisfaction)? (1 = very dissatisfied, 5 = very satisfied) | AG1: What actions could you take to better manage or reduce unplanned interruptions in your workday? (max 3) | AH1: What actions could your team take to better manage or reduce unplanned interruptions in your workday? (max 3) | AI1: What actions could your company take to better manage or reduce unplanned interruptions in your workday? (max 3) | AJ1: Would you be willing to participate in the next stage of the study — an interview? | AK1: Please provide an email address where we can contact you regarding an interview.
A2: 1 | B2: 45996.425 | C2: 45996.428 | D2: anonymous | F2: 18 - 24 | G2: Master’s degree | H2: Yes | I2: Hybrid | J2: 2 | K2: Finanance | L2: 501–5000 | M2: 1–3 years | N2: Data Scientist | O2: 8–12 people | P2: Research & development (R&D);Short-term / contract project; | Q2: I understand the definition of interruption | R2: 3–6 times | S2: 2 | T2: Team chats and messages (e.g., Teams, Slack, Jira);Meetings and quick conversations (e.g., ad-hoc calls, unexpected discussions); | U2: Implementation details; | V2: Colleagues at the same level (team members / peers) | W2: 2 | X2: 1 - 15 minutes | Y2: 2 | Z2: 1 - 15 minutes | AA2: No | AD2: 3 | AE2: 2 | AF2: 3 | AJ2: No
A3: 2 | B3: 45996.451 | C3: 45996.456 | D3: anonymous | F3: 30 - 34 | G3: Master’s degree | H3: Yes | I3: Hybrid | J3: 2 | K3: FINANCE | L3: More than 5000 | M3: 4–7 years | N3: Developer | O3: 8–12 people | P3: Internal product (e.g., company systems); | Q3: I understand the definition of interruption | R3: 3–6 times | S3: 2 | T3: Team chats and messages (e.g., Teams, Slack, Jira);Meetings and quick conversations (e.g., ad-hoc calls, unexpected discussions);System notifications and emails (alerts, reminders, work messages);Self-interruptions (voluntary context switching) — switching tasks on your own initiative (e.g., technical blockage, loss of focus); | U3: Technical questions or code questions;Notifications from communication tools;Organizational matters (e.g., meetings, planning); | V3: Colleagues at the same level (team members / peers) | W3: 2 | X3: 1 - 15 minutes | Y3: 2 | Z3: 15 - 30 minutes | AA3: Sometimes | AB3: NOT DISTURB STATUS IN TEAMS, IGNORING MESSAGES AFTER 12 | AC3: 2 | AD3: 4 | AE3: 3 | AF3: 4 | AJ3: No
A4: 3 | B4: 45996.497 | C4: 45996.499 | D4: anonymous | F4: 18 - 24 | G4: High school | H4: Yes | I4: On-site | J4: 3 | K4: Finance | L4: More than 5000 | M4: 1–3 years | N4: IT Manager | O4: 2–3 people | P4: Internal product (e.g., company systems);Commercial product (external client); | Q4: I understand the definition of interruption | R4: Less than 3 times per day | S4: 1 | T4: Meetings and quick conversations (e.g., ad-hoc calls, unexpected discussions); | U4: Code review; | V4: People in supporting or junior roles (e.g., less experienced team members) | W4: 4 | X4: 1 - 15 minutes | Y4: 2 | Z4: 30 - 60 minutes | AA4: Yes | AB4: . | AC4: 5 | AD4: 5 | AE4: 5 | AF4: 5 | AJ4: Yes
A5: 4 | B5: 45996.508 | C5: 45996.51 | D5: anonymous | F5: 18 - 24 | G5: High school | H5: Yes | I5: Hybrid | J5: 2 | K5: Office | L5: 101–500 | M5: 1–3 years | N5: IT Consultant | O5: 4–7 people | P5: Internal product (e.g., company systems); | Q5: I understand the definition of interruption | R5: Less than 3 times per day | S5: 1 | T5: Team chats and messages (e.g., Teams, Slack, Jira);Work environment (e.g., office noise, conversations, working on multiple projects simultaneously); | U5: Requests for help with environment issues; | V5: Colleagues at the same level (team members / peers) | W5: 4 | X5: 1 - 15 minutes | Y5: 2 | Z5: 15 - 30 minutes | AA5: No | AD5: 4 | AE5: 4 | AF5: 2 | AJ5: No
A6: 5 | B6: 45996.505 | C6: 45996.51 | D6: anonymous | F6: 18 - 24 | G6: High school | H6: Yes | I6: Hybrid | J6: 2 | K6: Finance | L6: 101–500 | M6: 1–3 years | N6: Tester | O6: 2–3 people | P6: Commercial product (external client); | Q6: I understand the definition of interruption | R6: 3–6 times | S6: 2 | T6: Team chats and messages (e.g., Teams, Slack, Jira); | U6: Implementation details; | V6: People in supporting or junior roles (e.g., less experienced team members) | W6: 3 | X6: 1 - 15 minutes | Y6: 2 | Z6: 15 - 30 minutes | AA6: No | AD6: 3 | AE6: 2 | AF6: 4 | AG6: 1. Block dedicated focus time on my calendar and mute non-critical notifications during those periods. 2. Set clearer expectations with colleagues about my availability and preferred communication channels. 3. Prioritize tasks at the start of each day so I can quickly refocus after any unavoidable interruptions | AH6: 1. Establish shared team norms for communication, including when to use chat, email, or meetings. 2. Consolidate non-urgent requests into daily or weekly sync points instead of ad-hoc interruptions. 3. Improve documentation and knowledge-sharing so fewer urgent “quick questions” arise. | AI6: 1. Promote a company-wide culture that respects focus time and minimizes unnecessary context switching. 2. Provide tools or processes that streamline task management and reduce last-minute escalations. 3. Align priorities and planning more consistently across departments to prevent unexpected work requests. | AJ6: No
A7: 6 | B7: 45996.75 | C7: 45996.753 | D7: anonymous | F7: 18 - 24 | G7: Master’s degree | H7: Yes | I7: Hybrid | J7: 2 | K7: finance | L7: 21–100 | M7: Less than 1 year | N7: IT Consultant | O7: 4–7 people | P7: Internal product (e.g., company systems);Commercial product (external client); | Q7: I understand the definition of interruption | R7: Less than 3 times per day | S7: 1 | T7: Meetings and quick conversations (e.g., ad-hoc calls, unexpected discussions);Team chats and messages (e.g., Teams, Slack, Jira); | U7: Notifications from communication tools;Requests for help with environment issues; | V7: Manager / product owner (formal supervisor or decision-maker) | W7: 3 | X7: 1 - 15 minutes | Y7: 2 | Z7: 15 - 30 minutes | AA7: No | AD7: 3 | AE7: 5 | AF7: 4 | AJ7: No
A8: 7 | B8: 45996.754 | C8: 45996.757 | D8: anonymous | F8: 18 - 24 | G8: Bachelor’s degree | H8: Yes | I8: Remote | J8: 1 | K8: Finance | L8: 101–500 | M8: Less than 1 year | N8: Tester | O8: 2–3 people | P8: Internal product (e.g., company systems); | Q8: I understand the definition of interruption | R8: 7–10 times | S8: 3 | T8: Team chats and messages (e.g., Teams, Slack, Jira);System notifications and emails (alerts, reminders, work messages);Work environment (e.g., office noise, conversations, working on multiple projects simultaneously); | U8: Implementation details;Notifications from communication tools; | V8: Manager / product owner (formal supervisor or decision-maker) | W8: 4 | X8: 1 - 15 minutes | Y8: 2 | Z8: 1 - 15 minutes | AA8: Sometimes | AB8: “do not disturb” | AC8: 3 | AD8: 3 | AE8: 5 | AF8: 2 | AJ8: No
A9: 8 | B9: 45996.758 | C9: 45996.76 | D9: anonymous | F9: 25 - 29 | G9: PhD | H9: Yes | I9: Remote | J9: 1 | K9: Game Dev | L9: 501–5000 | M9: 4–7 years | N9: Developer | O9: 8–12 people | P9: Commercial product (external client);Short-term / contract project;Research & development (R&D); | Q9: I understand the definition of interruption | R9: More than 10 times | S9: 4 | T9: Team chats and messages (e.g., Teams, Slack, Jira);Meetings and quick conversations (e.g., ad-hoc calls, unexpected discussions);System notifications and emails (alerts, reminders, work messages); | U9: Technical questions or code questions;Implementation details;Requests for help with environment issues;Code review;Notifications from communication tools;Organizational matters (e.g., meetings, planning); | V9: People in supporting or junior roles (e.g., less experienced team members) | W9: 4 | X9: 1 - 15 minutes | Y9: 2 | Z9: 30 - 60 minutes | AA9: Yes | AB9: Słuchawki z aktywnym tłumieniem szumów w celu wyciszenia hałasu, sztywne planowanie kolejności wykonywania zadań każdego dnia | AC9: 4 | AD9: 4 | AE9: 5 | AF9: 5 | AJ9: No
A10: 9 | B10: 45996.8 | C10: 45996.805 | D10: anonymous | F10: 25 - 29 | G10: Master’s degree | H10: Yes | I10: Hybrid | J10: 2 | K10: My company is operating in finance | L10: 21–100 | M10: 1–3 years | N10: Tester | O10: 4–7 people | P10: Short-term / contract project; | Q10: I understand the definition of interruption | R10: 3–6 times | S10: 2 | T10: Meetings and quick conversations (e.g., ad-hoc calls, unexpected discussions);System notifications and emails (alerts, reminders, work messages);Team chats and messages (e.g., Teams, Slack, Jira); | U10: Task status reminders;Requests for help with environment issues;Implementation details; | V10: Manager / product owner (formal supervisor or decision-maker) | W10: 3 | X10: 30 - 60 minutes | Y10: 4 | Z10: 15 - 30 minutes | AA10: No | AD10: 4 | AE10: 2 | AF10: 4 | AG10: Set clear focus blocks by scheduling dedicated time for deep work and temporarily muting non-urgent notifications. | AH10: Agree on shared communication norms, including expected response times and when to use specific channels. | AI10: Set organization-wide communication guidelines to reduce unnecessary pings and clarify expected response times. | AJ10: No
A11: 10 | B11: 45996.98 | C11: 45996.984 | D11: anonymous | F11: 18 - 24 | G11: Master’s degree | H11: Yes | I11: Remote | J11: 1 | K11: Fiance | L11: Under 20 employees | M11: 4–7 years | N11: Tester | O11: 4–7 people | P11: Internal product (e.g., company systems); | Q11: I understand the definition of interruption | R11: 3–6 times | S11: 2 | T11: System notifications and emails (alerts, reminders, work messages); | U11: Implementation details; | V11: Manager / product owner (formal supervisor or decision-maker) | W11: 5 | X11: 1 - 15 minutes | Y11: 2 | Z11: 15 - 30 minutes | AA11: Yes | AB11: I use the app on my phone | AC11: 4 | AD11: 4 | AE11: 4 | AF11: 4 | AG11: I plan my tasks, mute notifications, and set specific times to respond to messages. | AH11: use shared calendars for focus time | AI11: The company could introduce meeting free hours | AJ11: No
A12: 11 | B12: 45997.016 | C12: 45997.021 | D12: anonymous | F12: 18 - 24 | G12: High school | H12: Yes | I12: On-site | J12: 3 | K12: Finance | L12: 21–100 | M12: 1–3 years | N12: Developer | O12: 4–7 people | P12: Internal product (e.g., company systems);Short-term / contract project; | Q12: I understand the definition of interruption | R12: 7–10 times | S12: 3 | T12: Team chats and messages (e.g., Teams, Slack, Jira);System notifications and emails (alerts, reminders, work messages);Self-interruptions (voluntary context switching) — switching tasks on your own initiative (e.g., technical blockage, loss of focus); | U12: Technical questions or code questions; | V12: Colleagues at the same level (team members / peers) | W12: 4 | X12: 1 - 15 minutes | Y12: 2 | Z12: 15 - 30 minutes | AA12: No | AD12: 4 | AE12: 5 | AF12: 4 | AG12: Turn of my phone | AH12: Don't call me during if something is not important | AI12: Give workers personal rooms to work | AJ12: No
A13: 12 | B13: 45997.636 | C13: 45997.643 | D13: anonymous | F13: 18 - 24 | G13: High school | H13: Yes | I13: Hybrid | J13: 2 | K13: finance | L13: 101–500 | M13: 1–3 years | N13: Developer | O13: 2–3 people | P13: Short-term / contract project; | Q13: I understand the definition of interruption | R13: 3–6 times | S13: 2 | T13: Team chats and messages (e.g., Teams, Slack, Jira);Self-interruptions (voluntary context switching) — switching tasks on your own initiative (e.g., technical blockage, loss of focus); | U13: Task status reminders;Organizational matters (e.g., meetings, planning); | V13: Colleagues at the same level (team members / peers) | W13: 3 | X13: 1 - 15 minutes | Y13: 2 | Z13: 15 - 30 minutes | AA13: Yes | AB13: do not disturb | AC13: 4 | AD13: 4 | AE13: 2 | AF13: 4 | AG13: turn on: do not disturb in my phone | AH13: talk to each other and try to change that | AI13: . | AJ13: No
A14: 13 | B14: 45997.995 | C14: 45997.996 | D14: anonymous | F14: 18 - 24 | G14: Bachelor’s degree | H14: No | I14: On-site | J14: 3 | K14: Salwa | L14: 101–500 | M14: Less than 1 year | N14: Tester | O14: 4–7 people | P14: Internal product (e.g., company systems); | Q14: I understand the definition of interruption | R14: 3–6 times | S14: 2 | T14: System notifications and emails (alerts, reminders, work messages); | U14: Technical questions or code questions; | V14: Manager / product owner (formal supervisor or decision-maker) | W14: 4 | X14: 15 - 30 minutes | Y14: 3 | Z14: Immediately | AA14: No | AD14: 5 | AE14: 3 | AF14: 1 | AJ14: No
A15: 14 | B15: 45998.089 | C15: 45998.094 | D15: anonymous | F15: 18 - 24 | G15: High school | H15: No | I15: Hybrid | J15: 2 | K15: social media | L15: Under 20 employees | M15: Less than 1 year | N15: Tester | O15: 1 person (solo) | P15: Commercial product (external client); | Q15: I understand the definition of interruption | R15: 3–6 times | S15: 2 | T15: Team chats and messages (e.g., Teams, Slack, Jira);System notifications and emails (alerts, reminders, work messages);Self-interruptions (voluntary context switching) — switching tasks on your own initiative (e.g., technical blockage, loss of focus); | U15: Notifications from communication tools;Task status reminders;Organizational matters (e.g., meetings, planning); | V15: family | W15: 3 | X15: 15 - 30 minutes | Y15: 3 | Z15: 15 - 30 minutes | AA15: Yes | AB15: do not disturb status | AC15: 3 | AD15: 3 | AE15: 5 | AF15: 4 | AJ15: No
A16: 15 | B16: 45998.766 | C16: 45998.769 | D16: anonymous | F16: 18 - 24 | G16: Bachelor’s degree | H16: Yes | I16: On-site | J16: 3 | K16: finance | L16: 21–100 | M16: 1–3 years | N16: IT Consultant | O16: 2–3 people | P16: Internal product (e.g., company systems); | Q16: I understand the definition of interruption | R16: 3–6 times | S16: 2 | T16: Team chats and messages (e.g., Teams, Slack, Jira); | U16: Technical questions or code questions; | V16: Colleagues at the same level (team members / peers) | W16: 3 | X16: 1 - 15 minutes | Y16: 2 | Z16: 1 - 15 minutes | AA16: No | AD16: 4 | AE16: 3 | AF16: 5 | AG16: silence notifications | AH16: use shared calendars | AI16: set clear communication rules | AJ16: No
A17: 16 | B17: 45998.768 | C17: 45998.771 | D17: anonymous | F17: 30 - 34 | G17: Master’s degree | H17: Yes | I17: On-site | J17: 3 | K17: finance | L17: 101–500 | M17: 4–7 years | N17: IT Manager | O17: 13–20 people | P17: Internal product (e.g., company systems); | Q17: I understand the definition of interruption | R17: 7–10 times | S17: 3 | T17: Work environment (e.g., office noise, conversations, working on multiple projects simultaneously); | U17: Technical questions or code questions;Code review; | V17: Other departments (HR, sales, marketing) | W17: 3 | X17: 1 - 15 minutes | Y17: 2 | Z17: 15 - 30 minutes | AA17: No | AD17: 5 | AE17: 5 | AF17: 5 | AG17: Set dedicated focus time blocks with “Do Not Disturb” enabled to minimize spontaneous interruptions during deep-work tasks. Improve daily planning and prioritization, including reserving buffer time for unexpected issues to reduce context-switching. Communicate availability proactively so teammates know when I’m open for questions and when I need uninterrupted time. | AH17: 1. Establish clear communication windows for questions and discussions to avoid constant context switching. 2. Improve task planning and backlog refinement to reduce last-minute surprises. 3. Use a shared channel or ticketing system for non-urgent requests instead of direct ad-hoc messages. | AI17: 1. Provide guidelines for communication expectations, including response times and “focus time” etiquette. 2. Invest in better tooling and automation to reduce manual work and unexpected operational issues. 3. Ensure realistic workload and clearer prioritization so teams can focus without frequent unplanned shifts. | AJ17: No
A18: 17 | B18: 45998.795 | C18: 45998.796 | D18: anonymous | F18: 18 - 24 | G18: High school | H18: No | I18: Hybrid | J18: 2 | K18: finance | L18: 101–500 | M18: Less than 1 year | N18: Tester | O18: 4–7 people | P18: Short-term / contract project; | Q18: I understand the definition of interruption | R18: 7–10 times | S18: 3 | T18: Team chats and messages (e.g., Teams, Slack, Jira); | U18: Requests for help with environment issues; | V18: Other departments (HR, sales, marketing) | W18: 3 | X18: 1 - 15 minutes | Y18: 2 | Z18: 30 - 60 minutes | AA18: No | AD18: 4 | AE18: 2 | AF18: 3 | AG18: idk | AH18: idk | AI18: idk | AJ18: No
A19: 18 | B19: 45998.8 | C19: 45998.803 | D19: anonymous | F19: 18 - 24 | G19: High school | H19: No | I19: Remote | J19: 1 | K19: Insurances | L19: More than 5000 | M19: 1–3 years | N19: IT Consultant | O19: More than 20 people | P19: Short-term / contract project; | Q19: I understand the definition of interruption | R19: 3–6 times | S19: 2 | T19: Meetings and quick conversations (e.g., ad-hoc calls, unexpected discussions); | U19: Requests for help with environment issues; | V19: Colleagues at the same level (team members / peers) | W19: 3 | X19: 1 - 15 minutes | Y19: 2 | Z19: 1 - 15 minutes | AA19: Yes | AB19: Do not disturb mode, delaying less important task | AC19: 4 | AD19: 4 | AE19: 2 | AF19: 5 | AG19: Get a remote job | AH19: Interuptions are not really avoidable | AI19: Interruptions are not really avoidable | AJ19: No
A20: 19 | B20: 45998.805 | C20: 45998.808 | D20: anonymous | F20: 18 - 24 | G20: Bachelor’s degree | H20: Yes | I20: On-site | J20: 3 | K20: finance | L20: Under 20 employees | M20: 1–3 years | N20: IT Manager | O20: 2–3 people | P20: Internal product (e.g., company systems); | Q20: I understand the definition of interruption | R20: Less than 3 times per day | S20: 1 | T20: Meetings and quick conversations (e.g., ad-hoc calls, unexpected discussions); | U20: Technical questions or code questions; | V20: Client / end user | W20: 4 | X20: 15 - 30 minutes | Y20: 3 | Z20: 15 - 30 minutes | AA20: Sometimes | AB20: lock the door | AC20: 4 | AD20: 4 | AE20: 3 | AF20: 4 | AG20: idk | AJ20: No
A21: 20 | B21: 45999.333 | C21: 45999.337 | D21: anonymous | F21: 30 - 34 | G21: Master’s degree | H21: Yes | I21: Hybrid | J21: 2 | K21: Data Science | L21: More than 5000 | M21: 8–12 years | N21: Data Scientist | O21: 8–12 people | P21: Internal product (e.g., company systems); | Q21: I understand the definition of interruption | R21: 3–6 times | S21: 2 | T21: Team chats and messages (e.g., Teams, Slack, Jira);Meetings and quick conversations (e.g., ad-hoc calls, unexpected discussions);Work environment (e.g., office noise, conversations, working on multiple projects simultaneously); | U21: Implementation details;Technical questions or code questions;Notifications from communication tools;Organizational matters (e.g., meetings, planning); | V21: Colleagues at the same level (team members / peers) | W21: 4 | X21: 30 - 60 minutes | Y21: 4 | Z21: 15 - 30 minutes | AA21: Sometimes | AB21: Wyciszenie powiadomień, nie branie udziału w zbędnych spotkaniach | AC21: 4 | AD21: 5 | AE21: 4 | AF21: 4 | AJ21: No
A22: 21 | B22: 45999.511 | C22: 45999.517 | D22: anonymous | F22: 45 - 54 | G22: Master’s degree | H22: Yes | I22: Hybrid | J22: 2 | K22: finance | L22: More than 5000 | M22: 4–7 years | N22: Product & Proces Development Expert | O22: 13–20 people | P22: Commercial product (external client); | Q22: I understand the definition of interruption | R22: 3–6 times | S22: 2 | T22: Team chats and messages (e.g., Teams, Slack, Jira);Meetings and quick conversations (e.g., ad-hoc calls, unexpected discussions);Work environment (e.g., office noise, conversations, working on multiple projects simultaneously); | U22: Organizational matters (e.g., meetings, planning);Notifications from communication tools;Task status reminders; | V22: Colleagues at the same level (team members / peers) | W22: 3 | X22: 1 - 15 minutes | Y22: 2 | Z22: 1 - 15 minutes | AA22: No | AD22: 4 | AE22: 2 | AF22: 4 | AJ22: No
A23: 22 | B23: 45999.626 | C23: 45999.628 | D23: anonymous | F23: 18 - 24 | G23: Bachelor’s degree | H23: Yes | I23: Hybrid | J23: 2 | K23: Home devices | L23: More than 5000 | M23: 1–3 years | N23: Developer | O23: 4–7 people | P23: Internal product (e.g., company systems); | Q23: I understand the definition of interruption | R23: 3–6 times | S23: 2 | T23: Team chats and messages (e.g., Teams, Slack, Jira);Self-interruptions (voluntary context switching) — switching tasks on your own initiative (e.g., technical blockage, loss of focus); | U23: Technical questions or code questions;Organizational matters (e.g., meetings, planning); | V23: Colleagues at the same level (team members / peers) | W23: 3 | X23: Immediately | Y23: 1 | Z23: 1 - 15 minutes | AA23: No | AD23: 4 | AE23: 3 | AF23: 5 | AJ23: No
A24: 23 | B24: 45999.66 | C24: 45999.662 | D24: anonymous | F24: 18 - 24 | G24: Bachelor’s degree | H24: Yes | I24: Hybrid | J24: 2 | K24: Consulting | L24: More than 5000 | M24: 1–3 years | N24: Developer | O24: 8–12 people | P24: Short-term / contract project; | Q24: I understand the definition of interruption | R24: More than 10 times | S24: 4 | T24: Team chats and messages (e.g., Teams, Slack, Jira);Meetings and quick conversations (e.g., ad-hoc calls, unexpected discussions);System notifications and emails (alerts, reminders, work messages);Self-interruptions (voluntary context switching) — switching tasks on your own initiative (e.g., technical blockage, loss of focus); | U24: Notifications from communication tools;Task status reminders;Organizational matters (e.g., meetings, planning); | V24: Colleagues at the same level (team members / peers) | W24: 3 | X24: 1 - 15 minutes | Y24: 2 | Z24: 15 - 30 minutes | AA24: No | AD24: 4 | AE24: 3 | AF24: 4 | AJ24: No
A25: 24 | B25: 45999.681 | C25: 45999.682 | D25: anonymous | F25: 18 - 24 | G25: Bachelor’s degree | H25: Yes | I25: Remote | J25: 1 | K25: Enterprise | L25: 501–5000 | M25: 1–3 years | N25: Developer | O25: 4–7 people | P25: Commercial product (external client); | Q25: I understand the definition of interruption | R25: 3–6 times | S25: 2 | T25: Team chats and messages (e.g., Teams, Slack, Jira);System notifications and emails (alerts, reminders, work messages);Self-interruptions (voluntary context switching) — switching tasks on your own initiative (e.g., technical blockage, loss of focus); | U25: Code review;Requests for help with environment issues;Notifications from communication tools;Task status reminders;Organizational matters (e.g., meetings, planning); | V25: Colleagues at the same level (team members / peers) | W25: 2 | X25: 1 - 15 minutes | Y25: 2 | Z25: 1 - 15 minutes | AA25: No | AD25: 2 | AE25: 2 | AF25: 3 | AJ25: No
A26: 25 | B26: 45999.681 | C26: 45999.689 | D26: anonymous | F26: 18 - 24 | G26: Bachelor’s degree | H26: Yes | I26: On-site | J26: 3 | K26: Software development (smaller projects) | L26: 21–100 | M26: 1–3 years | N26: Developer | O26: 8–12 people | P26: Internal product (e.g., company systems);Commercial product (external client);Short-term / contract project; | Q26: I understand the definition of interruption | R26: 7–10 times | S26: 3 | T26: Work environment (e.g., office noise, conversations, working on multiple projects simultaneously);Self-interruptions (voluntary context switching) — switching tasks on your own initiative (e.g., technical blockage, loss of focus);Team chats and messages (e.g., Teams, Slack, Jira);Meetings and quick conversations (e.g., ad-hoc calls, unexpected discussions); | U26: Technical questions or code questions;Requests for help with environment issues;Implementation details; | V26: Colleagues at the same level (team members / peers) | W26: 4 | X26: Immediately | Y26: 1 | Z26: 1 - 15 minutes | AA26: Sometimes | AB26: Usually weating headphones means "i'm working" and my colleagues are used to me not listening them at all when i have them on. | AC26: 2 | AD26: 3 | AE26: 4 | AF26: 4 | AG26: Maybe somehow condition my teammates that i will not fix every problem at hand, start working remotely. | AH26: Enforce increasing task estimates after each interruption (management will see how much it can slow the work down), somehow enforce that many interruptions derive from poor documentation? if somebody asks you hows does it work it means you did not describe it properly. | AI26: I'd prefer the higher ups would not interfere in this. Maybe a middle manager could say something here. | AJ26: Yes | AK26: hubisoroka@gmail.com
A27: 26 | B27: 45999.738 | C27: 45999.741 | D27: anonymous | F27: 18 - 24 | G27: Bachelor’s degree | H27: Yes | I27: Remote | J27: 1 | K27: Finance | L27: 501–5000 | M27: 4–7 years | N27: Developer | O27: 4–7 people | P27: Internal product (e.g., company systems);Research & development (R&D); | Q27: I understand the definition of interruption | R27: 3–6 times | S27: 2 | T27: Team chats and messages (e.g., Teams, Slack, Jira);Meetings and quick conversations (e.g., ad-hoc calls, unexpected discussions);System notifications and emails (alerts, reminders, work messages);Self-interruptions (voluntary context switching) — switching tasks on your own initiative (e.g., technical blockage, loss of focus); | U27: Technical questions or code questions;Requests for help with environment issues;Code review;Notifications from communication tools;Organizational matters (e.g., meetings, planning); | V27: People in supporting or junior roles (e.g., less experienced team members) | W27: 3 | X27: 1 - 15 minutes | Y27: 2 | Z27: 1 - 15 minutes | AA27: No | AD27: 4 | AE27: 2 | AF27: 4 | AJ27: No
A28: 27 | B28: 45999.785 | C28: 45999.789 | D28: anonymous | F28: 18 - 24 | G28: Bachelor’s degree | H28: Yes | I28: Hybrid | J28: 2 | K28: embedded | L28: 101–500 | M28: 1–3 years | N28: Developer | O28: 8–12 people | P28: Commercial product (external client); | Q28: I understand the definition of interruption | R28: 3–6 times | S28: 2 | T28: Team chats and messages (e.g., Teams, Slack, Jira);Meetings and quick conversations (e.g., ad-hoc calls, unexpected discussions);Self-interruptions (voluntary context switching) — switching tasks on your own initiative (e.g., technical blockage, loss of focus); | U28: Requests for help with environment issues;Technical questions or code questions; | V28: Colleagues at the same level (team members / peers) | W28: 2 | X28: Immediately | Y28: 1 | Z28: 15 - 30 minutes | AA28: No | AD28: 3 | AE28: 2 | AF28: 3 | AJ28: No
A29: 28 | B29: 45999.874 | C29: 45999.887 | D29: anonymous | F29: 18 - 24 | G29: Bachelor’s degree | H29: Yes | I29: Remote | J29: 1 | K29: enterprise software | L29: 101–500 | M29: 1–3 years | N29: Developer | O29: 13–20 people | P29: Commercial product (external client); | Q29: I understand the definition of interruption | R29: 7–10 times | S29: 3 | T29: Team chats and messages (e.g., Teams, Slack, Jira);System notifications and emails (alerts, reminders, work messages); | U29: Requests for help with environment issues;Notifications from communication tools;Jira ticket status updates from clients; | V29: Client / end user | W29: 5 | X29: Immediately | Y29: 1 | Z29: 1 - 15 minutes | AA29: Sometimes | AB29: 1. transparency about my workload. When people know i have a lot to do they tend to interrupt me less often. 2. Not responding immediately after receiving a notification. | AC29: 4 | AD29: 4 | AE29: 5 | AF29: 4 | AG29: Change the job, because working in anything maintenance related is all about interruptions. | AH29: aggregate messages and send them less frequently | AI29: silent hours, tasks workflow change | AJ29: No
A30: 29 | B30: 45999.91 | C30: 45999.913 | D30: anonymous | F30: 18 - 24 | G30: Bachelor’s degree | H30: Yes | I30: Hybrid | J30: 2 | K30: CultureTech | L30: Under 20 employees | M30: 4–7 years | N30: Tech Lead | O30: 2–3 people | P30: Internal product (e.g., company systems);Commercial product (external client); | Q30: I understand the definition of interruption | R30: More than 10 times | S30: 4 | T30: System notifications and emails (alerts, reminders, work messages);Self-interruptions (voluntary context switching) — switching tasks on your own initiative (e.g., technical blockage, loss of focus);Work environment (e.g., office noise, conversations, working on multiple projects simultaneously); | U30: Organizational matters (e.g., meetings, planning);Technical questions or code questions;Implementation details;Requests for help with environment issues; | V30: Colleagues at the same level (team members / peers) | W30: 3 | X30: 1 - 15 minutes | Y30: 2 | Z30: 30 - 60 minutes | AA30: Yes | AB30: I just ignoring them or whenever I am taking sudden event, I am repeating in my mind "remember what were you doing just seconds ago" | AC30: 3 | AD30: 3 | AE30: 3 | AF30: 3 | AG30: Invest more into organisation/hr or assistant | AH30: Better time management and structure | AI30: Invest more into organisation/hr or assistant | AJ30: No
A31: 30 | B31: 46000.769 | C31: 46000.771 | D31: anonymous | F31: 18 - 24 | G31: Bachelor’s degree | H31: Yes | I31: Remote | J31: 1 | K31: IT assets management | L31: 21–100 | M31: 1–3 years | N31: Tester | O31: 4–7 people | P31: Internal product (e.g., company systems); | Q31: I understand the definition of interruption | R31: More than 10 times | S31: 4 | T31: Team chats and messages (e.g., Teams, Slack, Jira);Self-interruptions (voluntary context switching) — switching tasks on your own initiative (e.g., technical blockage, loss of focus);Work environment (e.g., office noise, conversations, working on multiple projects simultaneously); | U31: Requests for help with environment issues; | V31: Colleagues at the same level (team members / peers) | W31: 4 | X31: 1 - 15 minutes | Y31: 2 | Z31: 1 - 15 minutes | AA31: No | AD31: 3 | AE31: 4 | AF31: 4 | AJ31: Yes | AK31: adam.sudol36@gmail.com
A32: 31 | B32: 46000.849 | C32: 46000.855 | D32: anonymous | F32: 25 - 29 | G32: Master’s degree | H32: Yes | I32: Remote | J32: 1 | K32: data engineering | L32: 101–500 | M32: 1–3 years | N32: Developer | O32: 4–7 people | P32: Internal product (e.g., company systems); | Q32: I understand the definition of interruption | R32: Less than 3 times per day | S32: 1 | T32: Team chats and messages (e.g., Teams, Slack, Jira);Meetings and quick conversations (e.g., ad-hoc calls, unexpected discussions);Self-interruptions (voluntary context switching) — switching tasks on your own initiative (e.g., technical blockage, loss of focus); | U32: Technical questions or code questions;Implementation details; | V32: Colleagues at the same level (team members / peers) | W32: 3 | X32: 1 - 15 minutes | Y32: 2 | Z32: 1 - 15 minutes | AA32: No | AD32: 2 | AE32: 2 | AF32: 5 | AG32: 1. Add focus time 2. ignore messages until the task is finished or at least handled (not always possible) 3. Give better updated to my team so that they don't ask so many questions unnecessarily | AH32: 1. Refer to the documentation instead of texting 2. Prepare better before requesting something | AI32: Not sure, most interruptions come from colleagues directly. Maybe limit the overall number of meetings | AJ32: No
A33: 32 | B33: 46002.4 | C33: 46002.405 | D33: anonymous | F33: 45 - 54 | G33: Master’s degree | H33: No | I33: Hybrid | J33: 2 | K33: IT, bankowość | L33: Under 20 employees | M33: More than 12 years | N33: IT Consultant | O33: 8–12 people | P33: Internal product (e.g., company systems);Short-term / contract project; | Q33: I understand the definition of interruption | R33: More than 10 times | S33: 4 | T33: Team chats and messages (e.g., Teams, Slack, Jira);Meetings and quick conversations (e.g., ad-hoc calls, unexpected discussions);System notifications and emails (alerts, reminders, work messages);Self-interruptions (voluntary context switching) — switching tasks on your own initiative (e.g., technical blockage, loss of focus);Work environment (e.g., office noise, conversations, working on multiple projects simultaneously); | U33: Technical questions or code questions;Implementation details;Code review;Notifications from communication tools;Task status reminders;Organizational matters (e.g., meetings, planning); | V33: Colleagues at the same level (team members / peers) | W33: 3 | X33: 1 - 15 minutes | Y33: 2 | Z33: 1 - 15 minutes | AA33: No | AD33: 4 | AE33: 2 | AF33: 5 | AJ33: No
A34: 33 | B34: 46002.64 | C34: 46002.641 | D34: anonymous | F34: 30 - 34 | G34: Master’s degree | H34: No | I34: Hybrid | J34: 2 | K34: Finance & business | L34: More than 5000 | M34: 4–7 years | N34: IT Manager | O34: 13–20 people | P34: Internal product (e.g., company systems); | Q34: I understand the definition of interruption | R34: More than 10 times | S34: 4 | T34: Team chats and messages (e.g., Teams, Slack, Jira); | U34: Organizational matters (e.g., meetings, planning);Notifications from communication tools; | V34: Senior colleagues | W34: 4 | X34: 30 - 60 minutes | Y34: 4 | Z34: 30 - 60 minutes | AA34: No | AD34: 3 | AE34: 4 | AF34: 4 | AJ34: No
A35: 34 | B35: 46002.648 | C35: 46002.651 | D35: anonymous | F35: 30 - 34 | G35: Master’s degree | H35: Yes | I35: Hybrid | J35: 2 | K35: finance | L35: 501–5000 | M35: 8–12 years | N35: Developer | O35: 13–20 people | P35: Commercial product (external client); | Q35: I understand the definition of interruption | R35: 3–6 times | S35: 2 | T35: Work environment (e.g., office noise, conversations, working on multiple projects simultaneously);Team chats and messages (e.g., Teams, Slack, Jira);Meetings and quick conversations (e.g., ad-hoc calls, unexpected discussions); | U35: Organizational matters (e.g., meetings, planning);Technical questions or code questions; | V35: Colleagues at the same level (team members / peers) | W35: 2 | X35: 1 - 15 minutes | Y35: 2 | Z35: 15 - 30 minutes | AA35: No | AD35: 4 | AE35: 2 | AF35: 4 | AJ35: No
A36: 35 | B36: 46003.308 | C36: 46003.311 | D36: anonymous | F36: 30 - 34 | G36: High school | H36: Yes | I36: Remote | J36: 1 | K36: finance | L36: More than 5000 | M36: 8–12 years | N36: Tester | O36: More than 20 people | P36: Internal product (e.g., company systems);Commercial product (external client); | Q36: I understand the definition of interruption | R36: 7–10 times | S36: 3 | T36: Team chats and messages (e.g., Teams, Slack, Jira);Meetings and quick conversations (e.g., ad-hoc calls, unexpected discussions); | U36: Technical questions or code questions;Requests for help with environment issues; | V36: Colleagues at the same level (team members / peers) | W36: 5 | X36: 1 - 15 minutes | Y36: 2 | Z36: more than 60 minutes | AA36: No | AD36: 4 | AE36: 4 | AF36: 3 | AG36: More skilled workforce | AH36: know their role and learn systems they're working on | AI36: more work, less talk | AJ36: No
A37: 36 | B37: 46005.476 | C37: 46005.482 | D37: anonymous | F37: 45 - 54 | G37: Master’s degree | H37: Yes | I37: Hybrid | J37: 2 | K37: Telecom | L37: More than 5000 | M37: 8–12 years | N37: IT Manager | O37: 2–3 people | P37: Internal product (e.g., company systems); | Q37: I understand the definition of interruption | R37: Less than 3 times per day | S37: 1 | T37: Team chats and messages (e.g., Teams, Slack, Jira);Meetings and quick conversations (e.g., ad-hoc calls, unexpected discussions);System notifications and emails (alerts, reminders, work messages); | U37: Technical questions or code questions;Organizational matters (e.g., meetings, planning); | V37: Colleagues at the same level (team members / peers) | W37: 3 | X37: Immediately | Y37: 1 | Z37: 1 - 15 minutes | AA37: No | AD37: 5 | AE37: 4 | AF37: 5 | AG37: Set "do not interrupt" status | AH37: Better knowledge of documentation, consulting the documentation prior to interrupting | AI37: Introduce "Hyde Park time" - period in a workday where questions can be asked and eventual interruptions are more likely | AJ37: No
A38: 37 | B38: 46007.546 | C38: 46007.569 | D38: anonymous | F38: 25 - 29 | G38: Master’s degree | H38: Yes | I38: Hybrid | J38: 2 | K38: Finance | L38: More than 5000 | M38: 1–3 years | N38: Developer | O38: 8–12 people | P38: Internal product (e.g., company systems); | Q38: I understand the definition of interruption | R38: 3–6 times | S38: 2 | T38: Meetings and quick conversations (e.g., ad-hoc calls, unexpected discussions);Team chats and messages (e.g., Teams, Slack, Jira);System notifications and emails (alerts, reminders, work messages);Self-interruptions (voluntary context switching) — switching tasks on your own initiative (e.g., technical blockage, loss of focus); | U38: Technical questions or code questions;Code review;Requests for help with environment issues;Notifications from communication tools;Organizational matters (e.g., meetings, planning); | V38: Colleagues at the same level (team members / peers) | W38: 2 | X38: Immediately | Y38: 1 | Z38: 1 - 15 minutes | AA38: No | AD38: 4 | AE38: 2 | AF38: 4 | AG38: Reserve daily time slot for code reviews; verify your calendar at the beginning of the day; react as soon as possible to avoid cumulatimg those tasks | AH38: First verify (something) on your own and ask for help after that; dont accumulate extra things to do like f.e. code reviews, tickets testimg etc; react asap | AI38: Dont spam too much on mailbox with mails not related to my departament/position. Mimizie the amount of „unnecessary” meetings | AJ38: Yes | AK38: pilacki.lukasz@gmail.com
A39: 38 | B39: 46007.676 | C39: 46007.684 | D39: anonymous | F39: 18 - 24 | G39: Bachelor’s degree | H39: No | I39: Remote | J39: 1 | K39: technology consulting, IT projects (mainly Data/AI) | L39: More than 5000 | M39: Less than 1 year | N39: Data Analyst | O39: 13–20 people | P39: Commercial product (external client); | Q39: I understand the definition of interruption | R39: 7–10 times | S39: 3 | T39: Team chats and messages (e.g., Teams, Slack, Jira);Meetings and quick conversations (e.g., ad-hoc calls, unexpected discussions);System notifications and emails (alerts, reminders, work messages); | U39: Organizational matters (e.g., meetings, planning);Technical questions or code questions;Requests for help with environment issues;Notifications from communication tools; | V39: Colleagues at the same level (team members / peers) | W39: 4 | X39: 1 - 15 minutes | Y39: 2 | Z39: 15 - 30 minutes | AA39: No | AD39: 4 | AE39: 4 | AF39: 3 | AG39: set status to busy and turn off notifications | AH39: raise on the daily morning that they will need my help later and schedule it in calendar | AJ39: No
A40: 39 | B40: 46009.381 | C40: 46009.442 | D40: anonymous | F40: 18 - 24 | G40: Bachelor’s degree | H40: Yes | I40: Hybrid | J40: 2 | K40: Software for Universities | L40: 21–100 | M40: 1–3 years | N40: Developer | O40: 4–7 people | P40: Commercial product (external client); | Q40: I understand the definition of interruption | R40: Less than 3 times per day | S40: 1 | T40: Team chats and messages (e.g., Teams, Slack, Jira);Meetings and quick conversations (e.g., ad-hoc calls, unexpected discussions); | U40: Technical questions or code questions;Implementation details;Requests for help with environment issues; | V40: Most often I am the one who interrupts others by asking questions | W40: 2 | X40: Immediately | Y40: 1 | Z40: 1 - 15 minutes | AA40: No | AD40: 3 | AE40: 1 | AF40: 4 | AG40: Mute notifications, | AH40: Set rules about, when we can discuss things; | AI40: Limit the number of not necessary meetings, make rooms noise proof to reduce noise from other parts of office i.e. Kitchen | AJ40: No
A41: 40 | B41: 46010.36 | C41: 46010.364 | D41: anonymous | F41: 35-44 | G41: Master’s degree | H41: No | I41: Hybrid | J41: 2 | K41: Finance | L41: 501–5000 | M41: More than 12 years | N41: Magician | O41: More than 20 people | P41: Short-term / contract project;Research & development (R&D);Internal product (e.g., company systems); | Q41: I understand the definition of interruption | R41: 7–10 times | S41: 3 | T41: Team chats and messages (e.g., Teams, Slack, Jira);Meetings and quick conversations (e.g., ad-hoc calls, unexpected discussions);System notifications and emails (alerts, reminders, work messages);Work environment (e.g., office noise, conversations, working on multiple projects simultaneously); | U41: Technical questions or code questions;Requests for help with environment issues;Notifications from communication tools;Organizational matters (e.g., meetings, planning); | V41: People in supporting or junior roles (e.g., less experienced team members) | W41: 4 | X41: 1 - 15 minutes | Y41: 2 | Z41: 1 - 15 minutes | AA41: Yes | AB41: Focus time, block availability | AC41: 4 | AD41: 5 | AE41: 4 | AF41: 5 | AG41: avoid multitasking | AH41: prioritization | AI41: prioritization and better foundation | AJ41: No
A42: 41 | B42: 46010.455 | C42: 46010.462 | D42: anonymous | F42: 35-44 | G42: Master’s degree | H42: Yes | I42: Remote | J42: 1 | K42: Consumer Electronics | L42: 501–5000 | M42: 8–12 years | N42: Developer | O42: 4–7 people | P42: Internal product (e.g., company systems);Research & development (R&D); | Q42: I understand the definition of interruption | R42: 3–6 times | S42: 2 | T42: Team chats and messages (e.g., Teams, Slack, Jira);Self-interruptions (voluntary context switching) — switching tasks on your own initiative (e.g., technical blockage, loss of focus); | U42: Technical questions or code questions;Requests for help with environment issues;Code review;Organizational matters (e.g., meetings, planning); | V42: Colleagues at the same level (team members / peers) | W42: 3 | X42: Immediately | Y42: 1 | Z42: 15 - 30 minutes | AA42: No | AD42: 3 | AE42: 2 | AF42: 4 | AG42: Ignore any interruptions in chosen hours. Make better documentation, so I could just link it. | AH42: Agree on "silent hours" where we do not disturb anyone. | AI42: Agree on "silent hours" where we do not disturb anyone. | AJ42: Yes | AK42: p.borowy@protonmail.com
A43: 42 | B43: 46010.485 | C43: 46010.577 | D43: anonymous | F43: 35-44 | G43: Master’s degree | H43: No | I43: Hybrid | J43: 2 | K43: software | L43: More than 5000 | M43: Less than 1 year | N43: SQA | O43: 4–7 people | P43: Commercial product (external client);Research & development (R&D); | Q43: I understand the definition of interruption | R43: More than 10 times | S43: 4 | T43: Team chats and messages (e.g., Teams, Slack, Jira);System notifications and emails (alerts, reminders, work messages);Work environment (e.g., office noise, conversations, working on multiple projects simultaneously); | U43: Organizational matters (e.g., meetings, planning);clarifying tasks + scope; | V43: Manager / product owner (formal supervisor or decision-maker) | W43: 4 | X43: 1 - 15 minutes | Y43: 2 | Z43: 30 - 60 minutes | AA43: No | AD43: 4 | AE43: 4 | AF43: 2 | AG43: already participating in time management workshops, writing down tasks in the morning, prioritizing according to Eisenhower Matrix | AI43: clarify instructions and scope, be more transparent about upcoming tasks (many adhoc tasks with asap deadlines) | AJ43: No
A44: 43 | B44: 46010.904 | C44: 46010.908 | D44: anonymous | F44: 45 - 54 | G44: PhD | H44: Yes | I44: Remote | J44: 1 | K44: Automotive | L44: 21–100 | M44: More than 12 years | N44: IT Manager | O44: 8–12 people | P44: Commercial product (external client); | Q44: I understand the definition of interruption | R44: More than 10 times | S44: 4 | T44: Team chats and messages (e.g., Teams, Slack, Jira);Meetings and quick conversations (e.g., ad-hoc calls, unexpected discussions);System notifications and emails (alerts, reminders, work messages);Self-interruptions (voluntary context switching) — switching tasks on your own initiative (e.g., technical blockage, loss of focus); | U44: Technical questions or code questions;Requests for help with environment issues;Notifications from communication tools;Organizational matters (e.g., meetings, planning); | V44: Client / end user | W44: 4 | X44: 1 - 15 minutes | Y44: 2 | Z44: 15 - 30 minutes | AA44: No | AD44: 4 | AE44: 3 | AF44: 4 | AI44: Hire more people | AJ44: Yes | AK44: Jens.knodel@caruso-dstaplace.com
A45: 44 | B45: 46010.941 | C45: 46010.951 | D45: anonymous | F45: 30 - 34 | G45: PhD | H45: Yes | I45: On-site | J45: 3 | K45: Hardware | L45: More than 5000 | M45: 8–12 years | N45: Researcher | O45: 8–12 people | P45: Research & development (R&D); | Q45: I understand the definition of interruption | R45: 7–10 times | S45: 3 | T45: Self-interruptions (voluntary context switching) — switching tasks on your own initiative (e.g., technical blockage, loss of focus);Work environment (e.g., office noise, conversations, working on multiple projects simultaneously);Discussions with team members sitting nearby; | U45: Organizational matters (e.g., meetings, planning);Informal, non-work related ; | V45: People in supporting or junior roles (e.g., less experienced team members) | W45: 4 | X45: 1 - 15 minutes | Y45: 2 | Z45: 1 - 15 minutes | AA45: Yes | AB45: Put on noise cancelling headphones | AC45: 4 | AD45: 3 | AE45: 5 | AF45: 3 | AG45: go to the one person box, say to others that I'm super busy | AH45: Work from home (but it's not possible), focus more on work than socialising, for juniors: think before asking | AI45: Allow to work from home | AJ45: No
A46: 45 | B46: 46012.889 | C46: 46012.892 | D46: anonymous | F46: 35-44 | G46: Master’s degree | H46: Yes | I46: Hybrid | J46: 2 | K46: Oil&gas | L46: More than 5000 | M46: More than 12 years | N46: IT Manager | O46: More than 20 people | P46: Internal product (e.g., company systems); | Q46: I understand the definition of interruption | R46: 3–6 times | S46: 2 | T46: Team chats and messages (e.g., Teams, Slack, Jira);Meetings and quick conversations (e.g., ad-hoc calls, unexpected discussions);Work environment (e.g., office noise, conversations, working on multiple projects simultaneously); | U46: Organizational matters (e.g., meetings, planning);Notifications from communication tools; | V46: Colleagues at the same level (team members / peers) | W46: 4 | X46: 15 - 30 minutes | Y46: 3 | Z46: 1 - 15 minutes | AA46: Yes | AB46: Planed "absence "; don't disturb status | AC46: 3 | AD46: 4 | AE46: 2 | AF46: 4 | AG46: Being offline | AH46: Better planing of a workday | AI46: Less meetings | AJ46: No
A47: 46 | B47: 46013.474 | C47: 46013.479 | D47: anonymous | F47: 35-44 | G47: Master’s degree | H47: Yes | I47: Hybrid | J47: 2 | K47: Finance | L47: More than 5000 | M47: More than 12 years | N47: Developer | O47: 8–12 people | P47: Commercial product (external client); | Q47: I understand the definition of interruption | R47: More than 10 times | S47: 4 | T47: Team chats and messages (e.g., Teams, Slack, Jira);Meetings and quick conversations (e.g., ad-hoc calls, unexpected discussions);Self-interruptions (voluntary context switching) — switching tasks on your own initiative (e.g., technical blockage, loss of focus); | U47: Organizational matters (e.g., meetings, planning);Technical questions or code questions;Code review;Casual chats; | V47: Colleagues at the same level (team members / peers) | W47: 2 | X47: Immediately | Y47: 1 | Z47: Immediately | AA47: No | AD47: 3 | AE47: 2 | AF47: 4 | AG47: Headphones with noise cancelation; quickly respond "I can't talk" | AH47: Reduce meetings number, create silent hours (without chats), appoint one person to handle incoming current task | AI47: Reduce meetings number | AJ47: No
A48: 47 | B48: 46018.554 | C48: 46018.562 | D48: anonymous | F48: 45 - 54 | G48: PhD | H48: Yes | I48: Hybrid | J48: 2 | K48: retail | L48: More than 5000 | M48: More than 12 years | N48: Architect | O48: More than 20 people | P48: Internal product (e.g., company systems);Research & development (R&D); | Q48: I understand the definition of interruption | R48: 3–6 times | S48: 2 | T48: Team chats and messages (e.g., Teams, Slack, Jira);System notifications and emails (alerts, reminders, work messages);Self-interruptions (voluntary context switching) — switching tasks on your own initiative (e.g., technical blockage, loss of focus);Work environment (e.g., office noise, conversations, working on multiple projects simultaneously);Meetings and quick conversations (e.g., ad-hoc calls, unexpected discussions); | U48: Notifications from communication tools;Task status reminders;Organizational matters (e.g., meetings, planning); | V48: Colleagues at the same level (team members / peers) | W48: 4 | X48: Immediately | Y48: 1 | Z48: 15 - 30 minutes | AA48: Sometimes | AB48: change communicator status to "do not disturb", fake meeting placeholder | AC48: 3 | AD48: 3 | AE48: 4 | AF48: 5 | AG48: avoid interruption-prone environment e.g. put communicator to silent mode, work from home rather than from office in case of tasks demanding focus, avoid self-inducted interruptions : e.g. clean desk :) | AH48: better task planning and management, dedicated time slots for consultations, proper work arrangement - split work day for time dedicated for information exchange between team members and time dedicated to focus | AI48: office space arrangement that support focus (btw. company could do it but is not eager to do so) | AJ48: Yes | AK48: andrzej.ratkowski@pw.edu.pl
A49: 48 | B49: 46018.764 | C49: 46018.776 | D49: anonymous | F49: 35-44 | G49: PhD | H49: Yes | I49: Hybrid | J49: 2 | K49: Finance | L49: 101–500 | M49: More than 12 years | N49: IT Manager | O49: More than 20 people | P49: Internal product (e.g., company systems);Research & development (R&D); | Q49: I understand the definition of interruption | R49: 7–10 times | S49: 3 | T49: Team chats and messages (e.g., Teams, Slack, Jira);Meetings and quick conversations (e.g., ad-hoc calls, unexpected discussions);Self-interruptions (voluntary context switching) — switching tasks on your own initiative (e.g., technical blockage, loss of focus);Work environment (e.g., office noise, conversations, working on multiple projects simultaneously); | U49: Technical questions or code questions;Requests for help with environment issues;Notifications from communication tools;Task status reminders;Organizational matters (e.g., meetings, planning); | V49: People in supporting or junior roles (e.g., less experienced team members) | W49: 2 | X49: 1 - 15 minutes | Y49: 2 | Z49: 1 - 15 minutes | AA49: Yes | AB49: Use of the conference room during the meeting, status on teams | AC49: 3 | AD49: 4 | AE49: 3 | AF49: 5 | AG49: Limiting the hours during which I attend meetings | AH49: Collecting questions or topics and bringing them to me all at once | AI49: Establishing clear communication rules | AJ49: Yes | AK49: szymon.kijas@pw.edu.pl
A50: 49 | B50: 46021.926 | C50: 46021.929 | D50: anonymous | F50: 45 - 54 | G50: Master’s degree | H50: No | I50: On-site | J50: 3 | K50: Wholesale | L50: 501–5000 | M50: 8–12 years | N50: IT Manager | O50: More than 20 people | P50: Internal product (e.g., company systems); | Q50: I understand the definition of interruption | R50: More than 10 times | S50: 4 | T50: Team chats and messages (e.g., Teams, Slack, Jira);Meetings and quick conversations (e.g., ad-hoc calls, unexpected discussions);Self-interruptions (voluntary context switching) — switching tasks on your own initiative (e.g., technical blockage, loss of focus); | U50: Notifications from communication tools;Organizational matters (e.g., meetings, planning); | V50: Other departments (HR, sales, marketing) | W50: 4 | X50: 1 - 15 minutes | Y50: 2 | Z50: 1 - 15 minutes | AA50: Yes | AB50: Focus mode, calendar blocking | AC50: 3 | AD50: 3 | AE50: 4 | AF50: 4 | AJ50: No
A51: 50 | B51: 46022.372 | C51: 46022.379 | D51: anonymous | F51: 30 - 34 | G51: Bachelor’s degree | H51: Yes | I51: Remote | J51: 1 | K51: data engineering | L51: 501–5000 | M51: 8–12 years | N51: Architect | O51: 8–12 people | P51: Internal product (e.g., company systems);Commercial product (external client);Short-term / contract project;Research & development (R&D); | Q51: I understand the definition of interruption | R51: More than 10 times | S51: 4 | T51: Team chats and messages (e.g., Teams, Slack, Jira);Meetings and quick conversations (e.g., ad-hoc calls, unexpected discussions);System notifications and emails (alerts, reminders, work messages); | U51: Code review;Technical questions or code questions;Notifications from communication tools;Organizational matters (e.g., meetings, planning); | V51: People in supporting or junior roles (e.g., less experienced team members) | W51: 4 | X51: Immediately | Y51: 1 | Z51: 1 - 15 minutes | AA51: Yes | AB51: setting up blocked time in calendar (or meeting with myself only) | AC51: 5 | AD51: 5 | AE51: 3 | AF51: 5 | AG51: keep synchronous communication methods minimal, have AI read the messages and prioritize them (instead of most recent first) | AH51: reduce number of ceremonial meetings, define tasks more precisely, nothing - some interruptions are good, a result of working with people | AI51: delegate/hire more owners/stewards responsible for managing the interruptions, create a "focus hours" policy where communication is forbidden | AJ51: Yes | AK51: arek.zd@gmail.com
A52: 51 | B52: 46023.813 | C52: 46023.816 | D52: anonymous | F52: 18 - 24 | G52: Bachelor’s degree | H52: Yes | I52: Hybrid | J52: 2 | K52: finance, enterprise software | L52: 501–5000 | M52: 1–3 years | N52: data analyst | O52: 2–3 people | P52: Internal product (e.g., company systems); | Q52: I understand the definition of interruption | R52: 3–6 times | S52: 2 | T52: Team chats and messages (e.g., Teams, Slack, Jira);System notifications and emails (alerts, reminders, work messages);Self-interruptions (voluntary context switching) — switching tasks on your own initiative (e.g., technical blockage, loss of focus);Work environment (e.g., office noise, conversations, working on multiple projects simultaneously); | U52: Technical questions or code questions; | V52: Manager / product owner (formal supervisor or decision-maker) | W52: 2 | X52: 15 - 30 minutes | Y52: 3 | Z52: 1 - 15 minutes | AA52: No | AD52: 3 | AE52: 2 | AF52: 3 | AJ52: No
A53: 52 | B53: 46024.517 | C53: 46024.543 | D53: anonimowe | F53: 55 - 64 | G53: Master’s degree | H53: Yes | I53: Hybrid | J53: 2 | K53: IT system integration | L53: More than 5000 | M53: 4–7 years | N53: Solutions Manager | O53: 4–7 people | P53: Commercial product (external client) | Q53: I understand the definition of interruption | R53: Less than 3 times per day | S53: 1 | T53: Team chats and messages (e.g., Teams, Slack, Jira);Meetings and quick conversations (e.g., ad-hoc calls, unexpected discussions);Self-interruptions (voluntary context switching) — switching tasks on your own initiative (e.g., technical blockage, loss of focus);Work environment (e.g., office noise, conversations, working on multiple projects simultaneously);Personal, private issues | U53: Organizational matters (e.g., meetings, planning);Chanel requests. Big fix. Inquiry about project status. New project/opportunity assesments. Risk/issue management | V53: Manager / product owner (formal supervisor or decision-maker) | W53: 3 | X53: 1 - 15 minutes | Y53: 2 | Z53: 15 - 30 minutes | AA53: Sometimes | AB53: To-do list. Blocking time in calendar | AC53: 2 | AD53: 3 | AE53: 4 | AF53: 4 | AG53: Be invisible in Teams for some time (agreed with team) | AH53: Sprint retrospective. Reducing bug fix (eg by problem mamy). Setting ground rules for communication | AI53: Communication trainings. Guidelines/etiquette to use MS Teams | AJ53: No
A54: 53 | B54: 46024.747 | C54: 46024.755 | D54: anonimowe | F54: 18 - 24 | G54: Bachelor’s degree | H54: Yes | I54: Hybrid | J54: 2 | K54: Mobility | L54: More than 5000 | M54: 1–3 years | N54: Developer | O54: 8–12 people | P54: Internal product (e.g., company systems) | Q54: I understand the definition of interruption | R54: 3–6 times | S54: 2 | T54: Team chats and messages (e.g., Teams, Slack, Jira);Meetings and quick conversations (e.g., ad-hoc calls, unexpected discussions);Work environment (e.g., office noise, conversations, working on multiple projects simultaneously);System notifications and emails (alerts, reminders, work messages) | U54: Organizational matters (e.g., meetings, planning);Task status reminders;Notifications from communication tools;Requests for help with environment issues;Technical questions or code questions | V54: Client / end user | W54: 5 | X54: 1 - 15 minutes | Y54: 2 | Z54: 15 - 30 minutes | AA54: Sometimes | AB54: DND | AC54: 3 | AD54: 3 | AE54: 5 | AF54: 4 | AG54: Mute people immediately | AH54: Less meetings about the same thing | AI54: Stop returning to office because it has absolutely ZERO benefits and all it does is distract me | AJ54: Yes | AK54: jovanahinic420@gmail.com
A55: 54 | B55: 46024.781 | C55: 46024.788 | D55: anonimowe | F55: 55 - 64 | G55: PhD | H55: No | I55: Remote | J55: 1 | K55: Firearms education for professional operators, in a few words we develop XR rifle simulators (to use with a VARJO XR4 headset) for both the Department of Defense and Department of Justice, to virtually train both law enforcement officers and infantry in basic rifle operations in a virtual environment. | L55: 101–500 | M55: More than 12 years | N55: Tester | O55: 1 person (solo) | P55: Commercial product (external client) | Q55: I understand the definition of interruption | R55: Less than 3 times per day | S55: 1 | T55: I do not experience interruptions. I am a fully remote senior XR tester now, I receive the software build to test every Monday morning via email, and spend 36 hours (6 hours a day) with a XR4 headset on my face testing it on my own, and then every Saturday afternoon I email my feedback directly to the CEO. Again no interruptions. | U55: n/a | V55: n/a | W55: 1 | X55: Immediately | Y55: 1 | Z55: Immediately | AA55: No | AD55: 5 | AE55: 1 | AF55: 5 | AG55: Nothing, my work day is already perfectly efficient, they wouldn't pay me high six figures to work from home if it weren't. Although my income has more to do with my seniority level in the field (I started 4 decades ago in 1986 on this https://www.youtube.com/watch?v=G47bpduopSs ). | AJ55: No
A56: 55 | B56: 46024.822 | C56: 46024.836 | D56: anonimowe | F56: 35-44 | G56: Bachelor’s degree | H56: Yes | I56: Remote | J56: 1 | K56: SaaS, ads, enterprise, etc - whole lot of stuff | L56: More than 5000 | M56: More than 12 years | N56: Site Reliability Engineer | O56: 13–20 people | P56: Internal product (e.g., company systems) | Q56: I understand the definition of interruption | R56: More than 10 times | S56: 4 | T56: Team chats and messages (e.g., Teams, Slack, Jira);Meetings and quick conversations (e.g., ad-hoc calls, unexpected discussions);System notifications and emails (alerts, reminders, work messages);Self-interruptions (voluntary context switching) — switching tasks on your own initiative (e.g., technical blockage, loss of focus) | U56: Technical questions or code questions;Implementation details;Requests for help with environment issues;Code review;Notifications from communication tools;Organizational matters (e.g., meetings, planning) | V56: Colleagues at the same level (team members / peers) | W56: 5 | X56: 1 - 15 minutes | Y56: 2 | Z56: 1 - 15 minutes | AA56: No | AD56: 4 | AE56: 4 | AF56: 4 | AG56: Role change out of Site Reliability Engineering back to pure software development | AH56: lol | AI56: Put more resources towards making infrastructure work better, so fewer people get stuck and have to ask questions to get unblocked | AJ56: No
A57: 56 | B57: 46024.967 | C57: 46024.976 | D57: anonimowe | F57: 45 - 54 | G57: PhD | H57: Yes | I57: Remote | J57: 1 | K57: IT services | L57: 101–500 | M57: More than 12 years | N57: Developer | O57: 4–7 people | P57: Commercial product (external client);Short-term / contract project | Q57: I understand the definition of interruption | R57: Less than 3 times per day | S57: 1 | T57: Team chats and messages (e.g., Teams, Slack, Jira);System notifications and emails (alerts, reminders, work messages);Work environment (e.g., office noise, conversations, working on multiple projects simultaneously) | U57: Technical questions or code questions;Notifications from communication tools;Noise unrelated to work | V57: Colleagues at the same level (team members / peers) | W57: 5 | X57: 1 - 15 minutes | Y57: 2 | Z57: 30 - 60 minutes | AA57: No | AD57: 4 | AE57: 4 | AF57: 4 | AG57: Nothing | AH57: Nothing | AI57: Stop all irrelevant company-wide emails | AJ57: No
A58: 57 | B58: 46024.978 | C58: 46024.98 | D58: anonimowe | F58: 45 - 54 | G58: Master’s degree | H58: Yes | I58: Hybrid | J58: 2 | K58: Industrial devices, industrial process control, smart city, machine vision, deep learining | L58: More than 5000 | M58: More than 12 years | N58: IT Manager | O58: 13–20 people | P58: Research & development (R&D);Commercial product (external client) | Q58: I understand the definition of interruption | R58: 3–6 times | S58: 2 | T58: Team chats and messages (e.g., Teams, Slack, Jira);System notifications and emails (alerts, reminders, work messages);Self-interruptions (voluntary context switching) — switching tasks on your own initiative (e.g., technical blockage, loss of focus) | U58: Technical questions or code questions;Implementation details;Code review;Organizational matters (e.g., meetings, planning);Architecture, tech leader stuff | V58: Members of my teams | W58: 1 | X58: 1 - 15 minutes | Y58: 2 | Z58: Immediately | AA58: No | AD58: 4 | AE58: 2 | AF58: 4 | AJ58: No
A59: 58 | B59: 46024.986 | C59: 46024.989 | D59: anonimowe | F59: 18 - 24 | G59: High school | H59: Yes | I59: Remote | J59: 1 | K59: Pomoc informatyczna instalowanie systemów i sterowników | L59: Under 20 employees | M59: Less than 1 year | N59: Właściciel IT | O59: 13–20 people | P59: Commercial product (external client) | Q59: I understand the definition of interruption | R59: Less than 3 times per day | S59: 1 | T59: System notifications and emails (alerts, reminders, work messages) | U59: Task status reminders | V59: Colleagues at the same level (team members / peers) | W59: 2 | X59: Immediately | Y59: 1 | Z59: 1 - 15 minutes | AA59: Yes | AB59: Jestem Właścicielem to mogę robić przerwy kiedy chce | AC59: 5 | AD59: 5 | AE59: 1 | AF59: 5 | AJ59: No
A60: 59 | B60: 46025.005 | C60: 46025.016 | D60: anonimowe | F60: 35-44 | G60: Master’s degree | H60: Yes | I60: Remote | J60: 1 | K60: IT outsourcing, networking, cybersecurity | L60: More than 5000 | M60: 4–7 years | N60: Developer | O60: 8–12 people | P60: Commercial product (external client);Internal product (e.g., company systems);Research & development (R&D) | Q60: I understand the definition of interruption | R60: 3–6 times | S60: 2 | T60: Meetings and quick conversations (e.g., ad-hoc calls, unexpected discussions);Team chats and messages (e.g., Teams, Slack, Jira) | U60: Technical questions or code questions;Requests for help with environment issues;Task status reminders;Organizational matters (e.g., meetings, planning) | V60: Colleagues at the same level (team members / peers) | W60: 2 | X60: 1 - 15 minutes | Y60: 2 | Z60: 15 - 30 minutes | AA60: Yes | AB60: busy or dnd status, sometimes 'hide status' | AC60: 4 | AD60: 4 | AE60: 3 | AF60: 4 | AG60: being more assertive in response to some interruptions | AH60: do better work organization, make better documentation of work, writing down solved problems into documentation | AI60: maybe more courses to systematize knowledge? :P | AJ60: No
A61: 60 | B61: 46025.396 | C61: 46025.399 | D61: anonimowe | F61: 25 - 29 | G61: Master’s degree | H61: Yes | I61: On-site | J61: 3 | K61: enterprise software | L61: More than 5000 | M61: 4–7 years | N61: Developer | O61: 4–7 people | P61: Commercial product (external client) | Q61: I understand the definition of interruption | R61: Less than 3 times per day | S61: 1 | T61: Team chats and messages (e.g., Teams, Slack, Jira);Meetings and quick conversations (e.g., ad-hoc calls, unexpected discussions) | U61: Technical questions or code questions;Requests for help with environment issues;Code review | V61: People in supporting or junior roles (e.g., less experienced team members) | W61: 2 | X61: Immediately | Y61: 1 | Z61: 1 - 15 minutes | AA61: No | AD61: 3 | AE61: 4 | AF61: 1 | AG61: Nothing. I need to help people, who know less, because the whole project will take longer to finish | AI61: Employ more technical people, who are willing to learn more, that my current coworkers | AJ61: Yes
A62: 61 | B62: 46025.74 | C62: 46025.744 | D62: anonimowe | F62: 25 - 29 | G62: Bachelor’s degree | H62: Yes | I62: Hybrid | J62: 2 | K62: Services | L62: 21–100 | M62: 4–7 years | N62: Developer | O62: 4–7 people | P62: Internal product (e.g., company systems);Commercial product (external client) | Q62: I understand the definition of interruption | R62: 3–6 times | S62: 2 | T62: Team chats and messages (e.g., Teams, Slack, Jira);Meetings and quick conversations (e.g., ad-hoc calls, unexpected discussions);Self-interruptions (voluntary context switching) — switching tasks on your own initiative (e.g., technical blockage, loss of focus);Work environment (e.g., office noise, conversations, working on multiple projects simultaneously) | U62: Technical questions or code questions;Implementation details;Requests for help with environment issues;Organizational matters (e.g., meetings, planning) | V62: People in supporting or junior roles (e.g., less experienced team members) | W62: 4 | X62: 1 - 15 minutes | Y62: 2 | Z62: 15 - 30 minutes | AA62: Yes | AB62: Mostly DND or blocking calenders | AC62: 3 | AD62: 4 | AE62: 2 | AF62: 4 | AG62: Communicate focus times | AH62: Enfore focus time | AI62: Less meetings | AJ62: No
A63: 62 | B63: 46026.188 | C63: 46026.191 | D63: anonimowe | F63: 35-44 | G63: Master’s degree | H63: Yes | I63: Remote | J63: 1 | K63: Big tech | L63: More than 5000 | M63: More than 12 years | N63: Developer | O63: 4–7 people | P63: Internal product (e.g., company systems);Commercial product (external client) | Q63: I understand the definition of interruption | R63: 3–6 times | S63: 2 | T63: Team chats and messages (e.g., Teams, Slack, Jira);Meetings and quick conversations (e.g., ad-hoc calls, unexpected discussions);System notifications and emails (alerts, reminders, work messages);Self-interruptions (voluntary context switching) — switching tasks on your own initiative (e.g., technical blockage, loss of focus) | U63: Technical questions or code questions;Requests for help with environment issues;Code review;Notifications from communication tools;Organizational matters (e.g., meetings, planning) | V63: Colleagues at the same level (team members / peers) | W63: 4 | X63: 15 - 30 minutes | Y63: 3 | Z63: 30 - 60 minutes | AA63: Sometimes | AB63: Timers | AC63: 3 | AD63: 3 | AE63: 4 | AF63: 5 | AG63: Turn off some notifications | AJ63: No
A64: 63 | B64: 46027.034 | C64: 46027.038 | D64: anonimowe | F64: 18 - 24 | G64: Bachelor’s degree | H64: Yes | I64: Hybrid | J64: 2 | K64: Chem Engineering | L64: 501–5000 | M64: 1–3 years | N64: Developer | O64: 1 person (solo) | P64: Research & development (R&D);Internal product (e.g., company systems) | Q64: I understand the definition of interruption | R64: 7–10 times | S64: 3 | T64: Team chats and messages (e.g., Teams, Slack, Jira);Meetings and quick conversations (e.g., ad-hoc calls, unexpected discussions);System notifications and emails (alerts, reminders, work messages);Work environment (e.g., office noise, conversations, working on multiple projects simultaneously) | U64: Technical questions or code questions;Requests for help with environment issues | V64: Colleagues at the same level (team members / peers) | W64: 3 | X64: 1 - 15 minutes | Y64: 2 | Z64: 1 - 15 minutes | AA64: No | AD64: 2 | AE64: 2 | AF64: 4 | AJ64: No
A65: 64 | B65: 46029.369 | C65: 46029.372 | D65: anonimowe | F65: 18 - 24 | G65: Master’s degree | H65: Yes | I65: Remote | J65: 1 | K65: dietician | L65: 101–500 | M65: 4–7 years | N65: Developer | O65: 4–7 people | P65: Internal product (e.g., company systems);Research & development (R&D) | Q65: I understand the definition of interruption | R65: 3–6 times | S65: 2 | T65: Team chats and messages (e.g., Teams, Slack, Jira);Meetings and quick conversations (e.g., ad-hoc calls, unexpected discussions) | U65: Technical questions or code questions;Notifications from communication tools | V65: Manager / product owner (formal supervisor or decision-maker) | W65: 4 | X65: 1 - 15 minutes | Y65: 2 | Z65: 1 - 15 minutes | AA65: No | AD65: 2 | AE65: 4 | AF65: 2 | AG65: do not disturb | AH65: better planning | AI65: better planning | AJ65: No
A66: 65 | B66: 46037.538 | C66: 46037.543 | D66: anonimowe | F66: 30 - 34 | G66: Bachelor’s degree | H66: No | I66: Hybrid | J66: 2 | K66: Finance | L66: 501–5000 | M66: 1–3 years | N66: Tester | O66: 4–7 people | P66: Commercial product (external client) | Q66: I understand the definition of interruption | R66: More than 10 times | S66: 4 | T66: Team chats and messages (e.g., Teams, Slack, Jira);Meetings and quick conversations (e.g., ad-hoc calls, unexpected discussions);System notifications and emails (alerts, reminders, work messages);Work environment (e.g., office noise, conversations, working on multiple projects simultaneously);Self-interruptions (voluntary context switching) — switching tasks on your own initiative (e.g., technical blockage, loss of focus) | U66: Technical questions or code questions;Requests for help with environment issues;Notifications from communication tools;Organizational matters (e.g., meetings, planning) | V66: People in supporting or junior roles (e.g., less experienced team members) | W66: 3 | X66: Immediately | Y66: 1 | Z66: Immediately | AA66: Sometimes | AB66: Do not disturb status if online, wearing headphones if in the office | AC66: 3 | AD66: 4 | AE66: 2 | AF66: 4 | AG66: Dedicate blocked focus time | AH66: Schedule meetings for questions instead of asking ad hoc multiple times or use email instead of chat | AI66: Encourage people to use emails instead of chats so workers can reply at their own pace | AJ66: No
A67: 66 | B67: 46037.554 | C67: 46037.561 | D67: anonimowe | F67: 35-44 | G67: Master’s degree | H67: Yes | I67: Remote | J67: 1 | K67: finance software | L67: 501–5000 | M67: 1–3 years | N67: IT Consultant | O67: 13–20 people | P67: Commercial product (external client) | Q67: I understand the definition of interruption | R67: More than 10 times | S67: 4 | T67: Meetings and quick conversations (e.g., ad-hoc calls, unexpected discussions);Team chats and messages (e.g., Teams, Slack, Jira);Self-interruptions (voluntary context switching) — switching tasks on your own initiative (e.g., technical blockage, loss of focus);System failure or unplanned blockers (connection issues, missing configuration or invalid test files) | U67: Technical questions or code questions;Implementation details;Organizational matters (e.g., meetings, planning) | V67: Senior colleagues | W67: 4 | X67: 1 - 15 minutes | Y67: 2 | Z67: 1 - 15 minutes | AA67: Sometimes | AB67: Block calendar, days dedicated for a specific project | AC67: 2 | AD67: 4 | AE67: 4 | AF67: 3 | AG67: Use focus apps, disable notifications in Teams and Outlook, block my calendar | AH67: Create knowledge sharing repository with FAQ and already solved issues, store details about project status and progress of user stories in any kind of repository | AI67: No idea :-) maybe some sort of training? | AJ67: Yes | AK67: pawel.m.drab@gmail.com
A68: 67 | B68: 46037.561 | C68: 46037.563 | D68: anonimowe | F68: 35-44 | G68: Master’s degree | H68: Yes | I68: Remote | J68: 1 | K68: Finance | L68: 501–5000 | M68: 8–12 years | N68: IT Consultant | O68: 13–20 people | P68: Commercial product (external client) | Q68: I understand the definition of interruption | R68: Less than 3 times per day | S68: 1 | T68: Team chats and messages (e.g., Teams, Slack, Jira);Meetings and quick conversations (e.g., ad-hoc calls, unexpected discussions);Self-interruptions (voluntary context switching) — switching tasks on your own initiative (e.g., technical blockage, loss of focus) | U68: Technical questions or code questions;Requests for help with environment issues;Organizational matters (e.g., meetings, planning) | V68: Colleagues at the same level (team members / peers) | W68: 4 | X68: 15 - 30 minutes | Y68: 3 | Z68: 15 - 30 minutes | AA68: Yes | AB68: “do not disturb” status | AC68: 3 | AD68: 3 | AE68: 4 | AF68: 5 | AG68: Pomodor technice. Refuse help | AH68: More trainings | AI68: More trainings | AJ68: No
A69: 68 | B69: 46037.665 | C69: 46037.669 | D69: anonimowe | F69: 25 - 29 | G69: Bachelor’s degree | H69: Yes | I69: On-site | J69: 3 | K69: Finance | L69: 501–5000 | M69: Less than 1 year | N69: Consultant Investments | O69: 2–3 people | P69: Commercial product (external client) | Q69: I understand the definition of interruption | R69: Less than 3 times per day | S69: 1 | T69: Team chats and messages (e.g., Teams, Slack, Jira);Meetings and quick conversations (e.g., ad-hoc calls, unexpected discussions);Self-interruptions (voluntary context switching) — switching tasks on your own initiative (e.g., technical blockage, loss of focus) | U69: Requests for help with environment issues;Notifications from communication tools;Organizational matters (e.g., meetings, planning) | V69: Client / end user | W69: 3 | X69: 15 - 30 minutes | Y69: 3 | Z69: 1 - 15 minutes | AA69: No | AD69: 4 | AE69: 2 | AF69: 4 | AG69: Change my status to "do not disturb" | AH69: Going to the office can reduce the number of meetings I have on the day. | AI69: Reduce meeting overall. | AJ69: No
A70: 69 | B70: 46037.71 | C70: 46037.722 | D70: anonimowe | F70: 35-44 | G70: Bachelor’s degree | H70: Yes | I70: Hybrid | J70: 2 | K70: finance | L70: More than 5000 | M70: More than 12 years | N70: Tech Lead | O70: 1 person (solo) | P70: Internal product (e.g., company systems);Commercial product (external client) | Q70: I understand the definition of interruption | R70: 7–10 times | S70: 3 | T70: Team chats and messages (e.g., Teams, Slack, Jira);Meetings and quick conversations (e.g., ad-hoc calls, unexpected discussions);Self-interruptions (voluntary context switching) — switching tasks on your own initiative (e.g., technical blockage, loss of focus);Work environment (e.g., office noise, conversations, working on multiple projects simultaneously) | U70: Technical questions or code questions;Implementation details;Notifications from communication tools;Organizational matters (e.g., meetings, planning) | V70: Colleagues at the same level (team members / peers) | W70: 3 | X70: 1 - 15 minutes | Y70: 2 | Z70: 15 - 30 minutes | AA70: Yes | AB70: calendar blocking, DND | AC70: 3 | AD70: 4 | AE70: 4 | AF70: 4 | AG70: saying no to the request or delaying it , make sure to follow up on the request later, work on time that may have fewer collegues online and get "deep work" done | AH70: make sure to respect the notifications (DND) setup. | AI70: make everyone aware of effects of disruptions, encourage teams to have "quite zone" and "chatter zones", inter team communication should be bounded to be scheduled (no adhoc meetings outside teams). | AJ70: Yes | AK70: armu@simcorp.com
A71: 70 | B71: 46038.145 | C71: 46038.154 | D71: anonimowe | F71: 35-44 | G71: Bachelor’s degree | H71: No | I71: Hybrid | J71: 2 | K71: IT | L71: 501–5000 | M71: 1–3 years | N71: IT Manager | O71: 13–20 people | P71: Commercial product (external client) | Q71: I understand the definition of interruption | R71: 3–6 times | S71: 2 | T71: Team chats and messages (e.g., Teams, Slack, Jira);Meetings and quick conversations (e.g., ad-hoc calls, unexpected discussions);Self-interruptions (voluntary context switching) — switching tasks on your own initiative (e.g., technical blockage, loss of focus) | U71: Implementation details;Notifications from communication tools;Organizational matters (e.g., meetings, planning) | V71: Colleagues at the same level (team members / peers) | W71: 3 | X71: 30 - 60 minutes | Y71: 4 | Z71: more than 60 minutes | AA71: Sometimes | AB71: work remotely, do not disturb status, use noise cancelling headphones | AC71: 4 | AD71: 3 | AE71: 3 | AF71: 4 | AJ71: No
A72: 71 | B72: 46042.725 | C72: 46042.752 | D72: anonimowe | F72: 45 - 54 | G72: Bachelor’s degree | H72: Yes | I72: Remote | J72: 1 | K72: finance | L72: More than 5000 | M72: More than 12 years | N72: IT Consultant | O72: 13–20 people | P72: Commercial product (external client) | Q72: I understand the definition of interruption | R72: More than 10 times | S72: 4 | T72: Team chats and messages (e.g., Teams, Slack, Jira);Meetings and quick conversations (e.g., ad-hoc calls, unexpected discussions);System notifications and emails (alerts, reminders, work messages);Self-interruptions (voluntary context switching) — switching tasks on your own initiative (e.g., technical blockage, loss of focus);Work environment (e.g., office noise, conversations, working on multiple projects simultaneously) | U72: Technical questions or code questions;Implementation details;Notifications from communication tools;Organizational matters (e.g., meetings, planning) | V72: Colleagues at the same level (team members / peers) | W72: 3 | X72: 1 - 15 minutes | Y72: 2 | Z72: 1 - 15 minutes | AA72: Yes | AB72: close the communication tool (outlook, ms teams) not to receive any notifications; reserve the time in my calendar for a task so everybody could see that i am busy | AC72: 5 | AD72: 4 | AE72: 4 | AF72: 4 | AG72: review and reply to notifications only at a specified/reserved time slot during a day | AH72: ? | AI72: company wide knowledge sharing/webinars/elearning about interruptions, what those are, how to manage them, etc. | AJ72: No
A73: 72 | B73: 46043.238 | C73: 46043.331 | D73: anonimowe | F73: 25 - 29 | G73: Bachelor’s degree | H73: Yes | I73: Hybrid | J73: 2 | K73: Information Technology | L73: 501–5000 | M73: 8–12 years | N73: Project Manager | O73: More than 20 people | P73: Internal product (e.g., company systems);Commercial product (external client) | Q73: I understand the definition of interruption | R73: More than 10 times | S73: 4 | T73: Team chats and messages (e.g., Teams, Slack, Jira);Meetings and quick conversations (e.g., ad-hoc calls, unexpected discussions);Work environment (e.g., office noise, conversations, working on multiple projects simultaneously);System notifications and emails (alerts, reminders, work messages) | U73: Technical questions or code questions;Implementation details;Task status reminders;Organizational matters (e.g., meetings, planning) | V73: Colleagues at the same level (team members / peers) | W73: 3 | X73: 1 - 15 minutes | Y73: 2 | Z73: 1 - 15 minutes | AA73: Sometimes | AB73: setting MS team's status to "do not disturb" | AC73: 3 | AD73: 4 | AE73: 3 | AF73: 3 | AJ73: No
A74: 73 | B74: 46044.868 | C74: 46044.878 | D74: anonimowe | F74: 30 - 34 | G74: Master’s degree | H74: Yes | I74: Remote | J74: 1 | K74: Enterprise software | L74: Under 20 employees | M74: 1–3 years | N74: IT Manager | O74: 4–7 people | P74: Internal product (e.g., company systems);Short-term / contract project | Q74: I understand the definition of interruption | R74: 3–6 times | S74: 2 | T74: Team chats and messages (e.g., Teams, Slack, Jira);Work environment (e.g., office noise, conversations, working on multiple projects simultaneously);Meetings and quick conversations (e.g., ad-hoc calls, unexpected discussions) | U74: Implementation details;Technical questions or code questions;Organizational matters (e.g., meetings, planning);Requests for help with environment issues | V74: People in supporting or junior roles (e.g., less experienced team members) | W74: 3 | X74: 1 - 15 minutes | Y74: 2 | Z74: 15 - 30 minutes | AA74: Yes | AB74: Time-boxed focus blocks, Structured task prioritization, Controlled communication windows | AC74: 4 | AD74: 4 | AE74: 4 | AF74: 3 | AG74: Establish clear availability boundaries, Standardize intake for ad-hoc requests, Proactively eliminate common interruption sources | AH74: Use a single, prioritized intake process, Strengthen documentation and knowledge sharing | AI74: Protect the Sprint and Sprint Goal, Route interruptions through defined Scrum roles, Empower the Scrum Master to remove impediments | AJ74: Yes | AK74: hmarifuzzaman@gmail.com
A75: 74 | B75: 46045.331 | C75: 46045.349 | D75: anonimowe | F75: 35-44 | G75: PhD | H75: Yes | I75: Hybrid | J75: 2 | K75: Logistics | L75: More than 5000 | M75: More than 12 years | N75: IT Manager | O75: 8–12 people | P75: Internal product (e.g., company systems) | Q75: I understand the definition of interruption | R75: 3–6 times | S75: 2 | T75: Team chats and messages (e.g., Teams, Slack, Jira);Meetings and quick conversations (e.g., ad-hoc calls, unexpected discussions);System notifications and emails (alerts, reminders, work messages) | U75: Organizational matters (e.g., meetings, planning);Notifications from communication tools | V75: Senior colleagues | W75: 3 | X75: 1 - 15 minutes | Y75: 2 | Z75: 1 - 15 minutes | AA75: No | AD75: 4 | AE75: 2 | AF75: 4 | AG75: Block focus time, time slot for answering emails and other messages | AH75: Use shared channels, schedule regular stand ups | AI75: Establish company-wide focus hours, clear prioritization and escalation guidelines | AJ75: Yes | AK75: and.wilczynski@gmail.com

Sheet wybrane kolumny do analiz
A1: Id | B1: Frequency_ordinal | C1: disruptiveness | E1: Id | F1: Time_to_regain_focus_ordinal | G1: disruptiveness | I1: Id | J1: disruptiveness | K1: productivity | M1: Id | N1: disruptiveness | O1: satisfaction | Q1: Id | R1: work arrangement | S1: disruptiveness | T1: work arrangement ordinal
A2: 1 | B2: 2 | C2: 2 | E2: 1 | F2: 2 | G2: 2 | I2: 1 | J2: 2 | K2: 3 | M2: 1 | N2: 2 | O2: 3 | Q2: 1 | R2: Hybrid | S2: 2 | T2: 2
A3: 2 | B3: 2 | C3: 2 | E3: 2 | F3: 2 | G3: 2 | I3: 2 | J3: 2 | K3: 4 | M3: 2 | N3: 2 | O3: 4 | Q3: 2 | R3: Hybrid | S3: 2 | T3: 2
A4: 3 | B4: 1 | C4: 4 | E4: 3 | F4: 2 | G4: 4 | I4: 3 | J4: 4 | K4: 5 | M4: 3 | N4: 4 | O4: 5 | Q4: 3 | R4: On-site | S4: 4 | T4: 3
A5: 4 | B5: 1 | C5: 4 | E5: 4 | F5: 2 | G5: 4 | I5: 4 | J5: 4 | K5: 4 | M5: 4 | N5: 4 | O5: 2 | Q5: 4 | R5: Hybrid | S5: 4 | T5: 2
A6: 5 | B6: 2 | C6: 3 | E6: 5 | F6: 2 | G6: 3 | I6: 5 | J6: 3 | K6: 3 | M6: 5 | N6: 3 | O6: 4 | Q6: 5 | R6: Hybrid | S6: 3 | T6: 2
A7: 6 | B7: 1 | C7: 3 | E7: 6 | F7: 2 | G7: 3 | I7: 6 | J7: 3 | K7: 3 | M7: 6 | N7: 3 | O7: 4 | Q7: 6 | R7: Hybrid | S7: 3 | T7: 2
A8: 7 | B8: 3 | C8: 4 | E8: 7 | F8: 2 | G8: 4 | I8: 7 | J8: 4 | K8: 3 | M8: 7 | N8: 4 | O8: 2 | Q8: 7 | R8: Remote | S8: 4 | T8: 1
A9: 8 | B9: 4 | C9: 4 | E9: 8 | F9: 2 | G9: 4 | I9: 8 | J9: 4 | K9: 4 | M9: 8 | N9: 4 | O9: 5 | Q9: 8 | R9: Remote | S9: 4 | T9: 1
A10: 9 | B10: 2 | C10: 3 | E10: 9 | F10: 4 | G10: 3 | I10: 9 | J10: 3 | K10: 4 | M10: 9 | N10: 3 | O10: 4 | Q10: 9 | R10: Hybrid | S10: 3 | T10: 2
A11: 10 | B11: 2 | C11: 5 | E11: 10 | F11: 2 | G11: 5 | I11: 10 | J11: 5 | K11: 4 | M11: 10 | N11: 5 | O11: 4 | Q11: 10 | R11: Remote | S11: 5 | T11: 1
A12: 11 | B12: 3 | C12: 4 | E12: 11 | F12: 2 | G12: 4 | I12: 11 | J12: 4 | K12: 4 | M12: 11 | N12: 4 | O12: 4 | Q12: 11 | R12: On-site | S12: 4 | T12: 3
A13: 12 | B13: 2 | C13: 3 | E13: 12 | F13: 2 | G13: 3 | I13: 12 | J13: 3 | K13: 4 | M13: 12 | N13: 3 | O13: 4 | Q13: 12 | R13: Hybrid | S13: 3 | T13: 2
... A75: 74 | B75: 2 | C75: 3 | E75: 74 | F75: 2 | G75: 3 | I75: 74 | J75: 3 | K75: 4 | M75: 74 | N75: 3 | O75: 4 | Q75: 74 | R75: Hybrid | S75: 3 | T75: 2

Sheet Wielokrotny wybor rozbite
A1: Id | B1: What are the most common sources of interruptions in your work? | D1: Id | E1: InterruptionSource | G1: Id | H1: What are these interruptions usually about? | K1: Id | L1: Category
A2: 1 | B2: Team chats and messages (e.g., Teams, Slack, Jira);Meetings and quick conversations (e.g., ad-hoc calls, unexpected discussions); | D2: 1 | E2: Team chats and messages | G2: 1 | H2: Implementation details; | K2: 1 | L2: Implementation details
A3: 2 | B3: Team chats and messages (e.g., Teams, Slack, Jira);Meetings and quick conversations (e.g., ad-hoc calls, unexpected discussions);System notifications and emails (alerts, reminders, work messages);Self-interruptions (voluntary context switching) — switching tasks on your own initiative (e.g., technical blockage, loss of focus); | D3: 1 | E3: Meetings and quick conversations | G3: 2 | H3: Technical questions or code questions;Notifications from communication tools;Organizational matters (e.g., meetings, planning); | K3: 2 | L3: Technical questions or code questions
A4: 3 | B4: Meetings and quick conversations (e.g., ad-hoc calls, unexpected discussions); | D4: 2 | E4: Team chats and messages | G4: 3 | H4: Code review; | K4: 2 | L4: Notifications from communication tools
A5: 4 | B5: Team chats and messages (e.g., Teams, Slack, Jira);Work environment (e.g., office noise, conversations, working on multiple projects simultaneously); | D5: 2 | E5: Meetings and quick conversations | G5: 4 | H5: Requests for help with environment issues; | K5: 2 | L5: Organizational matters (e.g., meetings, planning)
A6: 5 | B6: Team chats and messages (e.g., Teams, Slack, Jira); | D6: 2 | E6: System notifications and emails | G6: 5 | H6: Implementation details; | K6: 3 | L6: Code review
A7: 6 | B7: Meetings and quick conversations (e.g., ad-hoc calls, unexpected discussions);Team chats and messages (e.g., Teams, Slack, Jira); | D7: 2 | E7: Self-interruptions | G7: 6 | H7: Notifications from communication tools;Requests for help with environment issues; | K7: 4 | L7: Requests for help with environment issues
A8: 7 | B8: Team chats and messages (e.g., Teams, Slack, Jira);System notifications and emails (alerts, reminders, work messages);Work environment (e.g., office noise, conversations, working on multiple projects simultaneously); | D8: 3 | E8: Meetings and quick conversations | G8: 7 | H8: Implementation details;Notifications from communication tools; | K8: 5 | L8: Implementation details
A9: 8 | B9: Team chats and messages (e.g., Teams, Slack, Jira);Meetings and quick conversations (e.g., ad-hoc calls, unexpected discussions);System notifications and emails (alerts, reminders, work messages); | D9: 4 | E9: Team chats and messages | G9: 8 | H9: Technical questions or code questions;Implementation details;Requests for help with environment issues;Code review;Notifications from communication tools;Organizational matters (e.g., meetings, planning); | K9: 6 | L9: Notifications from communication tools
A10: 9 | B10: Meetings and quick conversations (e.g., ad-hoc calls, unexpected discussions);System notifications and emails (alerts, reminders, work messages);Team chats and messages (e.g., Teams, Slack, Jira); | D10: 4 | E10: Work environment | G10: 9 | H10: Task status reminders;Requests for help with environment issues;Implementation details; | K10: 6 | L10: Requests for help with environment issues
A11: 10 | B11: System notifications and emails (alerts, reminders, work messages); | D11: 5 | E11: Team chats and messages | G11: 10 | H11: Implementation details; | K11: 7 | L11: Implementation details
A12: 11 | B12: Team chats and messages (e.g., Teams, Slack, Jira);System notifications and emails (alerts, reminders, work messages);Self-interruptions (voluntary context switching) — switching tasks on your own initiative (e.g., technical blockage, loss of focus); | D12: 6 | E12: Meetings and quick conversations | G12: 11 | H12: Technical questions or code questions; | K12: 7 | L12: Notifications from communication tools
A13: 12 | B13: Team chats and messages (e.g., Teams, Slack, Jira);Self-interruptions (voluntary context switching) — switching tasks on your own initiative (e.g., technical blockage, loss of focus); | D13: 6 | E13: Team chats and messages | G13: 12 | H13: Task status reminders;Organizational matters (e.g., meetings, planning); | K13: 8 | L13: Technical questions or code questions
... A75: 74 | B75: Team chats and messages (e.g., Teams, Slack, Jira);Meetings and quick conversations (e.g., ad-hoc calls, unexpected discussions);System notifications and emails (alerts, reminders, work messages) | D75: 32 | E75: Team chats and messages | G75: 74 | H75: Organizational matters (e.g., meetings, planning);Notifications from communication tools | K75: 32 | L75: Code review
D76: 32 | E76: Meetings and quick conversations | K76: 32 | L76: Notifications from communication tools
D77: 32 | E77: System notifications and emails | K77: 32 | L77: Task status reminders
D78: 32 | E78: Self-interruptions | K78: 32 | L78: Organizational matters (e.g., meetings, planning)
D79: 32 | E79: Work environment | K79: 33 | L79: Organizational matters (e.g., meetings, planning)
D80: 33 | E80: Team chats and messages | K80: 33 | L80: Notifications from communication tools
D81: 34 | E81: Work environment | K81: 34 | L81: Organizational matters (e.g., meetings, planning)
D82: 34 | E82: Team chats and messages | K82: 34 | L82: Technical questions or code questions
D83: 34 | E83: Meetings and quick conversations | K83: 35 | L83: Technical questions or code questions
D84: 35 | E84: Team chats and messages | K84: 35 | L84: Requests for help with environment issues
D85: 35 | E85: Meetings and quick conversations | K85: 36 | L85: Technical questions or code questions
D86: 36 | E86: Team chats and messages | K86: 36 | L86: Organizational matters (e.g., meetings, planning)
D87: 36 | E87: Meetings and quick conversations | K87: 37 | L87: Technical questions or code questions
... D210: 73 | E210: Meetings and quick conversations | K210: 74 | L210: Notifications from communication tools
D211: 74 | E211: Team chats and messages
D212: 74 | E212: Meetings and quick conversations
D213: 74 | E213: System notifications and emails

Sheet Open q1 labeled
A1: Question | B1: In which industry/domain does your company operate (e.g., finance, game development, enterprise software)?
A2: ID | B2: Answer | C2: Label
A3: 1 | B3: Finanance | C3: Finance
A4: 2 | B4: FINANCE | C4: Finance
A5: 3 | B5: Finance | C5: Finance
A6: 4 | B6: Office | C6: Enterprise Software
A7: 5 | B7: Finance | C7: Finance
A8: 6 | B8: finance | C8: Finance
A9: 7 | B9: Finance | C9: Finance
A10: 8 | B10: Game Dev | C10: Game Development
A11: 9 | B11: My company is operating in finance | C11: Finance
A12: 10 | B12: Fiance | C12: Finance
A13: 11 | B13: Finance | C13: Finance
A14: 12 | B14: finance | C14: Finance
... A72: 70 | B72: IT | C72: IT (General)
B76: Etykiety wierszy | C76: Liczba z ID
B77: Finance | C77: 31
B78: IT Services / Consulting | C78: 5
B79: Enterprise Software | C79: 4
B80: Data / AI | C80: 4
B81: Hardware / Embedded | C81: 4
B82: Retail | C82: 2
B83: Software Development | C83: 2
B84: Energy | C84: 1
B85: Other | C85: 1
B86: IT Support | C86: 1
B87: Chemical Engineering | C87: 1
B88: SaaS / Enterprise | C88: 1
... B102: Suma końcowa | C102: 70

Sheet Open q2 labeled
A1: Question | B1: What methods do you personally use to reduce or manage interruptions during your work? (max. 3)
A2: ID | B2: Answer | C2: Label | D2: Effectiveness of methods
A3: 1 | C3: No Strategy Reported | D3: =VLOOKUP(PersonalMethods[[#This Row],[ID]],Data!A:AC,29,FALSE) -> 0
A4: 2 | B4: NOT DISTURB STATUS IN TEAMS, IGNORING MESSAGES AFTER 12 | C4: Availability Signaling | D4: =VLOOKUP(PersonalMethods[[#This Row],[ID]],Data!A:AC,29,FALSE) -> 2
A5: 3 | B5: . | C5: No Strategy Reported | D5: =VLOOKUP(PersonalMethods[[#This Row],[ID]],Data!A:AC,29,FALSE) -> 5
A6: 4 | C6: No Strategy Reported | D6: =VLOOKUP(PersonalMethods[[#This Row],[ID]],Data!A:AC,29,FALSE) -> 0
A7: 5 | C7: No Strategy Reported | D7: =VLOOKUP(PersonalMethods[[#This Row],[ID]],Data!A:AC,29,FALSE) -> 0
A8: 6 | C8: No Strategy Reported | D8: =VLOOKUP(PersonalMethods[[#This Row],[ID]],Data!A:AC,29,FALSE) -> 0
A9: 7 | B9: “do not disturb” | C9: Availability Signaling | D9: =VLOOKUP(PersonalMethods[[#This Row],[ID]],Data!A:AC,29,FALSE) -> 3
A10: 8 | B10: Słuchawki z aktywnym tłumieniem szumów w celu wyciszenia hałasu, sztywne planowanie kolejności wykonywania zadań każdego dnia | C10: Noise Reduction | D10: =VLOOKUP(PersonalMethods[[#This Row],[ID]],Data!A:AC,29,FALSE) -> 4
A11: 8 | B11: Słuchawki z aktywnym tłumieniem szumów w celu wyciszenia hałasu, sztywne planowanie kolejności wykonywania zadań każdego dnia | C11: Task & Priority Management | D11: =VLOOKUP(PersonalMethods[[#This Row],[ID]],Data!A:AC,29,FALSE) -> 4
A12: 9 | C12: No Strategy Reported | D12: =VLOOKUP(PersonalMethods[[#This Row],[ID]],Data!A:AC,29,FALSE) -> 0
A13: 10 | B13: I use the app on my phone | C13: Self-regulation & Autonomy | D13: =VLOOKUP(PersonalMethods[[#This Row],[ID]],Data!A:AC,29,FALSE) -> 4
A14: 11 | C14: No Strategy Reported | D14: =VLOOKUP(PersonalMethods[[#This Row],[ID]],Data!A:AC,29,FALSE) -> 0
A15: 12 | B15: do not disturb | C15: Availability Signaling | D15: =VLOOKUP(PersonalMethods[[#This Row],[ID]],Data!A:AC,29,FALSE) -> 4
A16: 13 | C16: No Strategy Reported | D16: =VLOOKUP(PersonalMethods[[#This Row],[ID]],Data!A:AC,29,FALSE) -> 0
A17: 14 | B17: do not disturb status | C17: Availability Signaling | D17: =VLOOKUP(PersonalMethods[[#This Row],[ID]],Data!A:AC,29,FALSE) -> 3
A18: 15 | C18: No Strategy Reported | D18: =VLOOKUP(PersonalMethods[[#This Row],[ID]],Data!A:AC,29,FALSE) -> 0
A19: 16 | C19: No Strategy Reported | D19: =VLOOKUP(PersonalMethods[[#This Row],[ID]],Data!A:AC,29,FALSE) -> 0
A20: 17 | C20: No Strategy Reported | D20: =VLOOKUP(PersonalMethods[[#This Row],[ID]],Data!A:AC,29,FALSE) -> 0
A21: 18 | B21: Do not disturb mode, delaying less important task | C21: Availability Signaling | D21: =VLOOKUP(PersonalMethods[[#This Row],[ID]],Data!A:AC,29,FALSE) -> 4
A22: 18 | B22: Do not disturb mode, delaying less important task | C22: Task & Priority Management | D22: =VLOOKUP(PersonalMethods[[#This Row],[ID]],Data!A:AC,29,FALSE) -> 4
A23: 19 | B23: lock the door | C23: Physical / Context Isolation | D23: =VLOOKUP(PersonalMethods[[#This Row],[ID]],Data!A:AC,29,FALSE) -> 4
A24: 20 | B24: Wyciszenie powiadomień, nie branie udziału w zbędnych spotkaniach | C24: Availability Signaling | D24: =VLOOKUP(PersonalMethods[[#This Row],[ID]],Data!A:AC,29,FALSE) -> 4
A25: 20 | B25: Wyciszenie powiadomień, nie branie udziału w zbędnych spotkaniach | C25: Calendar & Time Blocking | D25: =VLOOKUP(PersonalMethods[[#This Row],[ID]],Data!A:AC,29,FALSE) -> 4
A26: 21 | C26: No Strategy Reported | D26: =VLOOKUP(PersonalMethods[[#This Row],[ID]],Data!A:AC,29,FALSE) -> 0
A27: 22 | C27: No Strategy Reported | D27: =VLOOKUP(PersonalMethods[[#This Row],[ID]],Data!A:AC,29,FALSE) -> 0
A28: 23 | C28: No Strategy Reported | D28: =VLOOKUP(PersonalMethods[[#This Row],[ID]],Data!A:AC,29,FALSE) -> 0
A29: 24 | C29: No Strategy Reported | D29: =VLOOKUP(PersonalMethods[[#This Row],[ID]],Data!A:AC,29,FALSE) -> 0
A30: 25 | B30: Usually weating headphones means "i'm working" and my colleagues are used to me not listening them at all when i have them on. | C30: Noise Reduction | D30: =VLOOKUP(PersonalMethods[[#This Row],[ID]],Data!A:AC,29,FALSE) -> 2
A31: 26 | C31: No Strategy Reported | D31: =VLOOKUP(PersonalMethods[[#This Row],[ID]],Data!A:AC,29,FALSE) -> 0
A32: 27 | C32: No Strategy Reported | D32: =VLOOKUP(PersonalMethods[[#This Row],[ID]],Data!A:AC,29,FALSE) -> 0
A33: 28 | B33: 1. transparency about my workload. When people know i have a lot to do they tend to interrupt me less often. 2. Not responding immediately after receiving a notification. | C33: Communication Practices | D33: =VLOOKUP(PersonalMethods[[#This Row],[ID]],Data!A:AC,29,FALSE) -> 4
A34: 29 | B34: I just ignoring them or whenever I am taking sudden event, I am repeating in my mind "remember what were you doing just seconds ago" | C34: Self-regulation & Autonomy | D34: =VLOOKUP(PersonalMethods[[#This Row],[ID]],Data!A:AC,29,FALSE) -> 3
A35: 29 | B35: I just ignoring them or whenever I am taking sudden event, I am repeating in my mind "remember what were you doing just seconds ago" | C35: Communication Practices | D35: =VLOOKUP(PersonalMethods[[#This Row],[ID]],Data!A:AC,29,FALSE) -> 3
A36: 30 | C36: No Strategy Reported | D36: =VLOOKUP(PersonalMethods[[#This Row],[ID]],Data!A:AC,29,FALSE) -> 0
A37: 31 | C37: No Strategy Reported | D37: =VLOOKUP(PersonalMethods[[#This Row],[ID]],Data!A:AC,29,FALSE) -> 0
A38: 32 | C38: No Strategy Reported | D38: =VLOOKUP(PersonalMethods[[#This Row],[ID]],Data!A:AC,29,FALSE) -> 0
A39: 33 | C39: No Strategy Reported | D39: =VLOOKUP(PersonalMethods[[#This Row],[ID]],Data!A:AC,29,FALSE) -> 0
A40: 34 | C40: No Strategy Reported | D40: =VLOOKUP(PersonalMethods[[#This Row],[ID]],Data!A:AC,29,FALSE) -> 0
A41: 35 | C41: No Strategy Reported | D41: =VLOOKUP(PersonalMethods[[#This Row],[ID]],Data!A:AC,29,FALSE) -> 0
A42: 36 | C42: No Strategy Reported | D42: =VLOOKUP(PersonalMethods[[#This Row],[ID]],Data!A:AC,29,FALSE) -> 0
A43: 37 | C43: No Strategy Reported | D43: =VLOOKUP(PersonalMethods[[#This Row],[ID]],Data!A:AC,29,FALSE) -> 0
A44: 38 | C44: No Strategy Reported | D44: =VLOOKUP(PersonalMethods[[#This Row],[ID]],Data!A:AC,29,FALSE) -> 0
A45: 39 | C45: No Strategy Reported | D45: =VLOOKUP(PersonalMethods[[#This Row],[ID]],Data!A:AC,29,FALSE) -> 0
A46: 40 | B46: Focus time, block availability | C46: Calendar & Time Blocking | D46: =VLOOKUP(PersonalMethods[[#This Row],[ID]],Data!A:AC,29,FALSE) -> 4
A47: 41 | C47: No Strategy Reported | D47: =VLOOKUP(PersonalMethods[[#This Row],[ID]],Data!A:AC,29,FALSE) -> 0
A48: 42 | C48: No Strategy Reported | D48: =VLOOKUP(PersonalMethods[[#This Row],[ID]],Data!A:AC,29,FALSE) -> 0
A49: 43 | C49: No Strategy Reported | D49: =VLOOKUP(PersonalMethods[[#This Row],[ID]],Data!A:AC,29,FALSE) -> 0
A50: 44 | B50: Put on noise cancelling headphones | C50: Noise Reduction | D50: =VLOOKUP(PersonalMethods[[#This Row],[ID]],Data!A:AC,29,FALSE) -> 4
A51: 45 | B51: Planed "absence "; don't disturb status | C51: Availability Signaling | D51: =VLOOKUP(PersonalMethods[[#This Row],[ID]],Data!A:AC,29,FALSE) -> 3
A52: 45 | B52: Planed "absence "; don't disturb status | C52: Calendar & Time Blocking | D52: =VLOOKUP(PersonalMethods[[#This Row],[ID]],Data!A:AC,29,FALSE) -> 3
A53: 46 | C53: No Strategy Reported | D53: =VLOOKUP(PersonalMethods[[#This Row],[ID]],Data!A:AC,29,FALSE) -> 0
A54: 47 | B54: change communicator status to "do not disturb", fake meeting placeholder | C54: Availability Signaling | D54: =VLOOKUP(PersonalMethods[[#This Row],[ID]],Data!A:AC,29,FALSE) -> 3
A55: 47 | B55: change communicator status to "do not disturb", fake meeting placeholder | C55: Calendar & Time Blocking | D55: =VLOOKUP(PersonalMethods[[#This Row],[ID]],Data!A:AC,29,FALSE) -> 3
A56: 48 | B56: Use of the conference room during the meeting, status on teams | C56: Physical / Context Isolation | D56: =VLOOKUP(PersonalMethods[[#This Row],[ID]],Data!A:AC,29,FALSE) -> 3
A57: 48 | B57: Use of the conference room during the meeting, status on teams | C57: Availability Signaling | D57: =VLOOKUP(PersonalMethods[[#This Row],[ID]],Data!A:AC,29,FALSE) -> 3
A58: 49 | B58: Focus mode, calendar blocking | C58: Calendar & Time Blocking | D58: =VLOOKUP(PersonalMethods[[#This Row],[ID]],Data!A:AC,29,FALSE) -> 3
A59: 50 | B59: setting up blocked time in calendar (or meeting with myself only) | C59: Calendar & Time Blocking | D59: =VLOOKUP(PersonalMethods[[#This Row],[ID]],Data!A:AC,29,FALSE) -> 5
A60: 51 | C60: No Strategy Reported | D60: =VLOOKUP(PersonalMethods[[#This Row],[ID]],Data!A:AC,29,FALSE) -> 0
A61: 52 | B61: To-do list. Blocking time in calendar | C61: Task & Priority Management | D61: =VLOOKUP(PersonalMethods[[#This Row],[ID]],Data!A:AC,29,FALSE) -> 2
A62: 52 | B62: To-do list. Blocking time in calendar | C62: Calendar & Time Blocking | D62: =VLOOKUP(PersonalMethods[[#This Row],[ID]],Data!A:AC,29,FALSE) -> 2
A63: 53 | B63: DND | C63: Availability Signaling | D63: =VLOOKUP(PersonalMethods[[#This Row],[ID]],Data!A:AC,29,FALSE) -> 3
A64: 54 | C64: No Strategy Reported | D64: =VLOOKUP(PersonalMethods[[#This Row],[ID]],Data!A:AC,29,FALSE) -> 0
A65: 55 | C65: No Strategy Reported | D65: =VLOOKUP(PersonalMethods[[#This Row],[ID]],Data!A:AC,29,FALSE) -> 0
A66: 56 | C66: No Strategy Reported | D66: =VLOOKUP(PersonalMethods[[#This Row],[ID]],Data!A:AC,29,FALSE) -> 0
A67: 57 | C67: No Strategy Reported | D67: =VLOOKUP(PersonalMethods[[#This Row],[ID]],Data!A:AC,29,FALSE) -> 0
A68: 58 | B68: Jestem Właścicielem to mogę robić przerwy kiedy chce | C68: Self-regulation & Autonomy | D68: =VLOOKUP(PersonalMethods[[#This Row],[ID]],Data!A:AC,29,FALSE) -> 5
A69: 59 | B69: busy or dnd status, sometimes 'hide status' | C69: Availability Signaling | D69: =VLOOKUP(PersonalMethods[[#This Row],[ID]],Data!A:AC,29,FALSE) -> 4
A70: 60 | C70: No Strategy Reported | D70: =VLOOKUP(PersonalMethods[[#This Row],[ID]],Data!A:AC,29,FALSE) -> 0
A71: 61 | B71: Mostly DND or blocking calenders | C71: Availability Signaling | D71: =VLOOKUP(PersonalMethods[[#This Row],[ID]],Data!A:AC,29,FALSE) -> 3
A72: 61 | B72: Mostly DND or blocking calenders | C72: Calendar & Time Blocking | D72: =VLOOKUP(PersonalMethods[[#This Row],[ID]],Data!A:AC,29,FALSE) -> 3
A73: 62 | B73: Timers | C73: Self-regulation & Autonomy | D73: =VLOOKUP(PersonalMethods[[#This Row],[ID]],Data!A:AC,29,FALSE) -> 3
A74: 63 | C74: No Strategy Reported | D74: =VLOOKUP(PersonalMethods[[#This Row],[ID]],Data!A:AC,29,FALSE) -> 0
A75: 64 | C75: No Strategy Reported | D75: =VLOOKUP(PersonalMethods[[#This Row],[ID]],Data!A:AC,29,FALSE) -> 0
A76: 65 | B76: Do not disturb status if online, wearing headphones if in the office | C76: Availability Signaling | D76: =VLOOKUP(PersonalMethods[[#This Row],[ID]],Data!A:AC,29,FALSE) -> 3
A77: 65 | B77: Do not disturb status if online, wearing headphones if in the office | C77: Noise Reduction | D77: =VLOOKUP(PersonalMethods[[#This Row],[ID]],Data!A:AC,29,FALSE) -> 3
A78: 66 | B78: Block calendar, days dedicated for a specific project | C78: Calendar & Time Blocking | D78: =VLOOKUP(PersonalMethods[[#This Row],[ID]],Data!A:AC,29,FALSE) -> 2
A79: 66 | B79: Block calendar, days dedicated for a specific project | C79: Task & Priority Management | D79: =VLOOKUP(PersonalMethods[[#This Row],[ID]],Data!A:AC,29,FALSE) -> 2
A80: 67 | B80: “do not disturb” status | C80: Availability Signaling | D80: =VLOOKUP(PersonalMethods[[#This Row],[ID]],Data!A:AC,29,FALSE) -> 3
A81: 68 | C81: No Strategy Reported | D81: =VLOOKUP(PersonalMethods[[#This Row],[ID]],Data!A:AC,29,FALSE) -> 0
A82: 69 | B82: calendar blocking, DND | C82: Calendar & Time Blocking | D82: =VLOOKUP(PersonalMethods[[#This Row],[ID]],Data!A:AC,29,FALSE) -> 3
A83: 69 | B83: calendar blocking, DND | C83: Availability Signaling | D83: =VLOOKUP(PersonalMethods[[#This Row],[ID]],Data!A:AC,29,FALSE) -> 3
A84: 70 | B84: work remotely, do not disturb status, use noise cancelling headphones | C84: Physical / Context Isolation | D84: =VLOOKUP(PersonalMethods[[#This Row],[ID]],Data!A:AC,29,FALSE) -> 4
A85: 70 | B85: work remotely, do not disturb status, use noise cancelling headphones | C85: Availability Signaling | D85: =VLOOKUP(PersonalMethods[[#This Row],[ID]],Data!A:AC,29,FALSE) -> 4
A86: 70 | B86: work remotely, do not disturb status, use noise cancelling headphones | C86: Noise Reduction | D86: =VLOOKUP(PersonalMethods[[#This Row],[ID]],Data!A:AC,29,FALSE) -> 4
A87: 71 | B87: close the communication tool (outlook, ms teams) not to receive any notifications; reserve the time in my calendar for a task so everybody could see that i am busy | C87: Availability Signaling | D87: =VLOOKUP(PersonalMethods[[#This Row],[ID]],Data!A:AC,29,FALSE) -> 5
A88: 71 | B88: close the communication tool (outlook, ms teams) not to receive any notifications; reserve the time in my calendar for a task so everybody could see that i am busy | C88: Calendar & Time Blocking | D88: =VLOOKUP(PersonalMethods[[#This Row],[ID]],Data!A:AC,29,FALSE) -> 5
A89: 72 | B89: setting MS team's status to "do not disturb" | C89: Availability Signaling | D89: =VLOOKUP(PersonalMethods[[#This Row],[ID]],Data!A:AC,29,FALSE) -> 3
A90: 73 | B90: Time-boxed focus blocks, Structured task prioritization, Controlled communication windows | C90: Calendar & Time Blocking | D90: =VLOOKUP(PersonalMethods[[#This Row],[ID]],Data!A:AC,29,FALSE) -> 4
A91: 73 | B91: Time-boxed focus blocks, Structured task prioritization, Controlled communication windows | C91: Task & Priority Management | D91: =VLOOKUP(PersonalMethods[[#This Row],[ID]],Data!A:AC,29,FALSE) -> 4
A92: 73 | B92: Time-boxed focus blocks, Structured task prioritization, Controlled communication windows | C92: Communication Practices | D92: =VLOOKUP(PersonalMethods[[#This Row],[ID]],Data!A:AC,29,FALSE) -> 4
A93: 74 | C93: No Strategy Reported | D93: =VLOOKUP(PersonalMethods[[#This Row],[ID]],Data!A:AC,29,FALSE) -> 0

Sheet Open q3 labeled
A1: Question | B1: What actions could you take to better manage or reduce unplanned interruptions in your workday? (max 3)
A2: Survey Id | B2: Answer | C2: Label
A3: 1 | C3: No Action / Not Applicable
A4: 2 | C4: No Action / Not Applicable
A5: 3 | C5: No Action / Not Applicable
A6: 4 | C6: No Action / Not Applicable
A7: 5 | B7: Block dedicated focus time on my calendar and mute non-critical notifications during those periods. | C7: Calendar Blocking
A8: 5 | B8: Block dedicated focus time on my calendar and mute non-critical notifications during those periods. | C8: Notification Muting
A9: 5 | B9: Set clearer expectations with colleagues about my availability and preferred communication channels. | C9: Communication Norms
A10: 5 | B10: Prioritize tasks at the start of each day so I can quickly refocus after any unavoidable interruptions | C10: Task Prioritization
A11: 6 | C11: No Action / Not Applicable
A12: 7 | C12: No Action / Not Applicable
A13: 8 | C13: No Action / Not Applicable
A14: 9 | B14: Set clear focus blocks by scheduling dedicated time for deep work and temporarily muting non-urgent notifications. | C14: Calendar Blocking
A15: 9 | B15: Set clear focus blocks by scheduling dedicated time for deep work and temporarily muting non-urgent notifications. | C15: Notification Muting
A16: 10 | B16: I plan my tasks, mute notifications, and set specific times to respond to messages. | C16: Task Planning
A17: 10 | B17: I plan my tasks, mute notifications, and set specific times to respond to messages. | C17: Notification Muting
A18: 10 | B18: I plan my tasks, mute notifications, and set specific times to respond to messages. | C18: Delayed Response
A19: 11 | B19: Turn of my phone | C19: Device Shutdown / Offline
A20: 12 | B20: turn on: do not disturb in my phone | C20: Do Not Disturb / Status
A21: 13 | C21: No Action / Not Applicable
A22: 14 | C22: No Action / Not Applicable
A23: 15 | B23: silence notifications | C23: Notification Muting
A24: 16 | B24: Set dedicated focus time blocks with “Do Not Disturb” enabled to minimize spontaneous interruptions during deep-work tasks. | C24: Calendar Blocking
A25: 16 | B25: Set dedicated focus time blocks with “Do Not Disturb” enabled to minimize spontaneous interruptions during deep-work tasks. | C25: Do Not Disturb / Status
A26: 16 | B26: Improve daily planning and prioritization, including reserving buffer time for unexpected issues to reduce context-switching. | C26: Task Planning
A27: 16 | B27: Communicate availability proactively so teammates know when I’m open for questions and when I need uninterrupted time. | C27: Communication Norms
A28: 17 | B28: idk | C28: No Action / Not Applicable
A29: 18 | B29: Get a remote job | C29: Remote Work
A30: 19 | B30: idk | C30: No Action / Not Applicable
A31: 20 | C31: No Action / Not Applicable
A32: 21 | C32: No Action / Not Applicable
A33: 22 | C33: No Action / Not Applicable
A34: 23 | C34: No Action / Not Applicable
A35: 24 | C35: No Action / Not Applicable
A36: 25 | B36: Maybe somehow condition my teammates that i will not fix every problem at hand, start working remotely. | C36: Boundary Setting
A37: 25 | B37: Maybe somehow condition my teammates that i will not fix every problem at hand, start working remotely. | C37: Remote Work
A38: 26 | C38: No Action / Not Applicable
A39: 27 | C39: No Action / Not Applicable
A40: 28 | B40: Change the job, because working in anything maintenance related is all about interruptions. | C40: Role / Job Change
A41: 29 | B41: Invest more into organisation/hr or assistant | C41: Organizational Support
A42: 30 | C42: No Action / Not Applicable
A43: 31 | B43: Add focus time | C43: Focus Time
A44: 31 | B44: ignore messages until the task is finished or at least handled (not always possible) | C44: Delayed Response
A45: 31 | B45: Give better updated to my team so that they don't ask so many questions unnecessarily | C45: Communication Norms
A46: 32 | C46: No Action / Not Applicable
A47: 33 | C47: No Action / Not Applicable
A48: 34 | C48: No Action / Not Applicable
A49: 35 | B49: More skilled workforce | C49: Organizational Change
A50: 36 | B50: Set "do not interrupt" status | C50: Do Not Disturb / Status
A51: 37 | B51: Reserve daily time slot for code reviews; verify your calendar at the beginning of the day; react as soon as possible to avoid cumulatimg those tasks | C51: Calendar Blocking
A52: 37 | B52: Reserve daily time slot for code reviews; verify your calendar at the beginning of the day; react as soon as possible to avoid cumulatimg those tasks | C52: Task Planning
A53: 38 | B53: set status to busy and turn off notifications | C53: Do Not Disturb / Status
A54: 38 | B54: set status to busy and turn off notifications | C54: Notification Muting
A55: 39 | B55: Mute notifications, | C55: Notification Muting
A56: 40 | B56: avoid multitasking | C56: Task Focus / Single-tasking
A57: 41 | B57: Ignore any interruptions in chosen hours. | C57: Boundary Setting
A58: 41 | B58: Make better documentation, so I could just link it. | C58: Documentation Improvement
A59: 42 | B59: already participating in time management workshops, writing down tasks in the morning, prioritizing according to Eisenhower Matrix | C59: Time Management Training
A60: 42 | B60: already participating in time management workshops, writing down tasks in the morning, prioritizing according to Eisenhower Matrix | C60: Task Prioritization
A61: 43 | C61: No Action / Not Applicable
A62: 44 | B62: go to the one person box, say to others that I'm super busy | C62: Physical Isolation
A63: 44 | B63: go to the one person box, say to others that I'm super busy | C63: Boundary Setting
A64: 45 | B64: Being offline | C64: Device Shutdown / Offline
A65: 46 | B65: Headphones with noise cancelation; quickly respond "I can't talk" | C65: Noise Cancelling / Headphones
A66: 46 | B66: Headphones with noise cancelation; quickly respond "I can't talk" | C66: Boundary Setting
A67: 47 | B67: avoid interruption-prone environment e.g. put communicator to silent mode | C67: Notification Muting
A68: 47 | B68: work from home rather than from office in case of tasks demanding focus | C68: Remote Work
A69: 47 | B69: avoid self-inducted interruptions : e.g. clean desk :) | C69: Self-Discipline
A70: 48 | B70: Limiting the hours during which I attend meetings | C70: Meeting Reduction
A71: 49 | C71: No Action / Not Applicable
A72: 50 | B72: keep synchronous communication methods minimal, have AI read the messages and prioritize them (instead of most recent first) | C72: Asynchronous Communication
A73: 50 | B73: keep synchronous communication methods minimal, have AI read the messages and prioritize them (instead of most recent first) | C73: AI Assistance
A74: 51 | C74: No Action / Not Applicable
A75: 52 | B75: Be invisible in Teams for some time (agreed with team) | C75: Do Not Disturb / Status
A76: 53 | B76: Mute people immediately | C76: Notification Muting
A77: 54 | B77: Nothing, my work day is already perfectly efficient, they wouldn't pay me high six figures to work from home if it weren't. | C77: No Action / Not Applicable
A78: 55 | B78: Role change out of Site Reliability Engineering back to pure software development | C78: Role / Job Change
A79: 56 | B79: Nothing | C79: No Action / Not Applicable
A80: 57 | C80: No Action / Not Applicable
A81: 58 | C81: No Action / Not Applicable
A82: 59 | B82: being more assertive in response to some interruptions | C82: Boundary Setting
A83: 60 | B83: Nothing. I need to help people, who know less, because the whole project will take longer to finish | C83: No Action / Not Applicable
A84: 61 | B84: Communicate focus times | C84: Communication Norms
A85: 62 | B85: Turn off some notifications | C85: Notification Muting
A86: 63 | C86: No Action / Not Applicable
A87: 64 | B87: do not disturb | C87: Do Not Disturb / Status
A88: 65 | B88: Dedicate blocked focus time | C88: Calendar Blocking
A89: 66 | B89: Use focus apps, disable notifications in Teams and Outlook, block my calendar | C89: Focus / Productivity App
A90: 66 | B90: Use focus apps, disable notifications in Teams and Outlook, block my calendar | C90: Notification Muting
A91: 66 | B91: Use focus apps, disable notifications in Teams and Outlook, block my calendar | C91: Calendar Blocking
A92: 67 | B92: Pomodor technice. Refuse help | C92: Time Management Technique
A93: 67 | B93: Pomodor technice. Refuse help | C93: Boundary Setting
A94: 68 | B94: Change my status to "do not disturb" | C94: Do Not Disturb / Status
A95: 69 | B95: saying no to the request or delaying it , make sure to follow up on the request later | C95: Boundary Setting
A96: 69 | B96: work on time that may have fewer collegues online and get "deep work" done | C96: Off-hours / Deep Work
A97: 70 | C97: No Action / Not Applicable
B101: Etykiety wierszy | C101: Liczba z Survey Id
B102: No Action / Not Applicable | C102: 32
B103: Notification Muting | C103: 10
...

Sheet Open q4 labeled
A1: Question | B1: What actions could your team take to better manage or reduce unplanned interruptions in your workday? (max 3)
A2: ID | B2: Answer | C2: Label
A3: 1 | C3: No Action / Not Applicable
A4: 2 | C4: No Action / Not Applicable
A5: 3 | C5: No Action / Not Applicable
A6: 4 | C6: No Action / Not Applicable
A7: 5 | B7: Establish shared team norms for communication, including when to use chat, email, or meetings. | C7: Team Communication Norms
A8: 5 | B8: Consolidate non-urgent requests into daily or weekly sync points instead of ad-hoc interruptions. | C8: Request Aggregation
A9: 5 | B9: Improve documentation and knowledge-sharing so fewer urgent “quick questions” arise. | C9: Documentation Improvement
A10: 6 | C10: No Action / Not Applicable
A11: 7 | C11: No Action / Not Applicable
A12: 8 | C12: No Action / Not Applicable
A13: 9 | B13: Agree on shared communication norms, including expected response times and when to use specific channels. | C13: Team Communication Norms
A14: 10 | B14: use shared calendars for focus time | C14: Shared Calendar / Focus Time
A15: 11 | B15: Don't call me during if something is not important | C15: Communication Rules
A16: 12 | B16: talk to each other and try to change that | C16: Team Awareness / Culture
A17: 13 | C17: No Action / Not Applicable
A18: 14 | C18: No Action / Not Applicable
A19: 15 | B19: use shared calendars | C19: Shared Calendar
A20: 16 | B20: Establish clear communication windows for questions and discussions to avoid constant context switching. | C20: Communication Windows
A21: 16 | B21: Improve task planning and backlog refinement to reduce last-minute surprises. | C21: Task Planning
A22: 16 | B22: Use a shared channel or ticketing system for non-urgent requests instead of direct ad-hoc messages. | C22: Asynchronous / Ticket-Based Communication
A23: 17 | B23: idk | C23: No Action / Not Applicable
A24: 18 | B24: Interuptions are not really avoidable | C24: No Action / Not Applicable
A25: 19 | C25: No Action / Not Applicable
A26: 20 | C26: No Action / Not Applicable
A27: 21 | C27: No Action / Not Applicable
A28: 22 | C28: No Action / Not Applicable
A29: 23 | C29: No Action / Not Applicable
A30: 24 | C30: No Action / Not Applicable
A31: 25 | B31: Enforce increasing task estimates after each interruption (management will see how much it can slow the work down) | C31: Impact Awareness / Metrics
A32: 25 | B32: interruptions derive from poor documentation | C32: Documentation Improvement
A33: 26 | C33: No Action / Not Applicable
A34: 27 | C34: No Action / Not Applicable
A35: 28 | B35: aggregate messages and send them less frequently | C35: Request Aggregation
A36: 29 | B36: Better time management and structure | C36: Task Planning
A37: 30 | C37: No Action / Not Applicable
A38: 31 | B38: Refer to the documentation instead of texting | C38: Documentation Usage
A39: 31 | B39: Prepare better before requesting something | C39: Request Quality Improvement
A40: 32 | C40: No Action / Not Applicable
A41: 33 | C41: No Action / Not Applicable
A42: 34 | C42: No Action / Not Applicable
A43: 35 | B43: know their role and learn systems they're working on | C43: Role Clarity / Training
A44: 36 | B44: Better knowledge of documentation, consulting the documentation prior to interrupting | C44: Documentation Usage
A45: 37 | B45: First verify on your own and ask for help after that | C45: Self-Sufficiency
A46: 37 | B46: react asap | C46: Task Prioritization
A47: 38 | B47: raise on the daily morning that they will need my help later and schedule it in calendar | C47: Advance Scheduling
A48: 39 | B48: Set rules about, when we can discuss things; | C48: Communication Rules
A49: 40 | B49: prioritization | C49: Task Prioritization
A50: 41 | B50: Agree on "silent hours" where we do not disturb anyone | C50: Silent Hours / Focus Time
A51: 42 | C51: No Action / Not Applicable
A52: 43 | C52: No Action / Not Applicable
A53: 44 | B53: Work from home (but it's not possible) | C53: Remote Work
A54: 44 | B54: focus more on work than socialising | C54: Team Focus Culture
A55: 44 | B55: for juniors: think before asking | C55: Self-Sufficiency
A56: 45 | B56: Better planing of a workday | C56: Task Planning
A57: 46 | B57: Reduce meetings number | C57: Meeting Reduction
A58: 46 | B58: create silent hours (without chats) | C58: Silent Hours / Focus Time
A59: 46 | B59: appoint one person to handle incoming current task | C59: Interruptions Gatekeeper
A60: 47 | B60: better task planning and management | C60: Task Planning
A61: 47 | B61: dedicated time slots for consultations | C61: Scheduled Consultations
A62: 47 | B62: split work day for information exchange and focus | C62: Structured Workday
A63: 48 | B63: Collecting questions or topics and bringing them to me all at once | C63: Request Aggregation
A64: 49 | C64: No Action / Not Applicable
A65: 50 | B65: reduce number of ceremonial meetings | C65: Meeting Reduction
A66: 50 | B66: define tasks more precisely | C66: Task Definition
A67: 50 | B67: some interruptions are good | C67: No Action / Not Applicable
A68: 51 | C68: No Action / Not Applicable
A69: 52 | B69: Sprint retrospective | C69: Process Improvement
A70: 52 | B70: Reducing bug fix | C70: Quality Improvement
A71: 52 | B71: Setting ground rules for communication | C71: Team Communication Norms
A72: 53 | B72: Less meetings about the same thing | C72: Meeting Reduction
A73: 54 | C73: No Action / Not Applicable
A74: 55 | B74: lol | C74: No Action / Not Applicable
A75: 56 | B75: Nothing | C75: No Action / Not Applicable
A76: 57 | C76: No Action / Not Applicable
A77: 58 | C77: No Action / Not Applicable
A78: 59 | B78: do better work organization | C78: Work Organization
A79: 59 | B79: make better documentation of work | C79: Documentation Improvement
A80: 59 | B80: writing down solved problems into documentation | C80: Knowledge Base
A81: 60 | C81: No Action / Not Applicable
A82: 61 | B82: Enfore focus time | C82: Focus Time Enforcement
A83: 62 | C83: No Action / Not Applicable
A84: 63 | C84: No Action / Not Applicable
A85: 64 | B85: better planning | C85: Task Planning
A86: 65 | B86: Schedule meetings for questions instead of asking ad hoc multiple times | C86: Scheduled Consultations
A87: 65 | B87: use email instead of chat | C87: Asynchronous Communication
A88: 66 | B88: Create knowledge sharing repository with FAQ and already solved issues | C88: Knowledge Repository
A89: 66 | B89: store details about project status and progress | C89: Project Transparency
A90: 67 | B90: More trainings | C90: Training / Skill Development
A91: 68 | B91: Going to the office can reduce the number of meetings I have on the day | C91: Work Arrangement Change
A92: 69 | B92: make sure to respect the notifications (DND) setup | C92: Respect Focus Status
A93: 70 | C93: No Action / Not Applicable
B98: Etykiety wierszy | C98: Liczba z ID
B99: No Action / Not Applicable | C99: 37
B100: Task Planning | C100: 5
B101: Team Communication Norms | C101: 3
B102: Documentation Improvement | C102: 3
B103: Meeting Reduction | C103: 3
B104: Request Aggregation | C104: 3
...

Sheet Open q5 labeled
A1: Question | B1: What actions could your company take to better manage or reduce unplanned interruptions in your workday? (max 3)
A2: Survey Id | B2: Answer | C2: Label
A3: 1 | C3: No Action / Not Applicable
A4: 2 | C4: No Action / Not Applicable
A5: 3 | C5: No Action / Not Applicable
A6: 4 | C6: No Action / Not Applicable
A7: 5 | B7: Promote a company-wide culture that respects focus time and minimizes unnecessary context switching. | C7: Focus Culture
A8: 5 | B8: Provide tools or processes that streamline task management and reduce last-minute escalations. | C8: Tooling / Process Improvement
A9: 5 | B9: Align priorities and planning more consistently across departments to prevent unexpected work requests. | C9: Cross-Team Planning
A10: 6 | C10: No Action / Not Applicable
A11: 7 | C11: No Action / Not Applicable
A12: 8 | C12: No Action / Not Applicable
A13: 9 | B13: Set organization-wide communication guidelines to reduce unnecessary pings and clarify expected response times. | C13: Company Communication Guidelines
A14: 10 | B14: The company could introduce meeting free hours | C14: Meeting-Free Time
A15: 11 | B15: Give workers personal rooms to work | C15: Office Space for Focus
A16: 12 | B16: . | C16: No Action / Not Applicable
A17: 13 | C17: No Action / Not Applicable
A18: 14 | C18: No Action / Not Applicable
A19: 15 | B19: set clear communication rules | C19: Company Communication Guidelines
A20: 16 | B20: Provide guidelines for communication expectations, including response times and “focus time” etiquette. | C20: Company Communication Guidelines
A21: 16 | B21: Invest in better tooling and automation to reduce manual work and unexpected operational issues. | C21: Tooling / Automation
A22: 16 | B22: Ensure realistic workload and clearer prioritization so teams can focus without frequent unplanned shifts. | C22: Workload & Prioritization
A23: 17 | B23: idk | C23: No Action / Not Applicable
A24: 18 | B24: Interruptions are not really avoidable | C24: No Action / Not Applicable
A25: 19 | C25: No Action / Not Applicable
A26: 20 | C26: No Action / Not Applicable
A27: 21 | C27: No Action / Not Applicable
A28: 22 | C28: No Action / Not Applicable
A29: 23 | C29: No Action / Not Applicable
A30: 24 | C30: No Action / Not Applicable
A31: 25 | B31: I'd prefer the higher ups would not interfere in this. Maybe a middle manager could say something here. | C31: Decentralized Decision-Making
A32: 26 | C32: No Action / Not Applicable
A33: 27 | C33: No Action / Not Applicable
A34: 28 | B34: silent hours | C34: Silent Hours / Focus Policy
A35: 28 | B35: tasks workflow change | C35: Process Improvement
A36: 29 | B36: Invest more into organisation/hr or assistant | C36: Organizational Support Roles
A37: 30 | C37: No Action / Not Applicable
A38: 31 | B38: limit the overall number of meetings | C38: Meeting Reduction
A39: 32 | C39: No Action / Not Applicable
A40: 33 | C40: No Action / Not Applicable
A41: 34 | C41: No Action / Not Applicable
A42: 35 | B42: more work, less talk | C42: Focus-Oriented Culture
A43: 36 | B43: Introduce "Hyde Park time" - period in a workday where questions can be asked and eventual interruptions are more likely | C43: Scheduled Interruption Windows
A44: 37 | B44: Dont spam too much on mailbox with mails not related to my departament/position | C44: Email Policy
A45: 37 | B45: Mimizie the amount of „unnecessary” meetings | C45: Meeting Reduction
A46: 38 | C46: No Action / Not Applicable
A47: 39 | B47: Limit the number of not necessary meetings | C47: Meeting Reduction
A48: 39 | B48: make rooms noise proof to reduce noise from other parts of office | C48: Office Noise Reduction
A49: 40 | B49: prioritization and better foundation | C49: Prioritization & Planning
A50: 41 | B50: Agree on "silent hours" where we do not disturb anyone. | C50: Silent Hours / Focus Policy
A51: 42 | B51: clarify instructions and scope | C51: Clarity of Requirements
A52: 42 | B52: be more transparent about upcoming tasks | C52: Task Transparency
A53: 43 | B53: Hire more people | C53: Staffing Increase
A54: 44 | B54: Allow to work from home | C54: Remote Work Policy
A55: 45 | B55: Less meetings | C55: Meeting Reduction
A56: 46 | B56: Reduce meetings number | C56: Meeting Reduction
A57: 47 | B57: office space arrangement that support focus | C57: Office Space for Focus
A58: 48 | B58: Establishing clear communication rules | C58: Company Communication Guidelines
A59: 49 | C59: No Action / Not Applicable
A60: 50 | B60: delegate/hire more owners/stewards responsible for managing the interruptions | C60: Interruptions Ownership
A61: 50 | B61: create a "focus hours" policy where communication is forbidden | C61: Focus Hours Policy
A62: 51 | C62: No Action / Not Applicable
A63: 52 | B63: Communication trainings | C63: Communication Training
A64: 52 | B64: Guidelines/etiquette to use MS Teams | C64: Tool Usage Guidelines
A65: 53 | B65: Stop returning to office because it has absolutely ZERO benefits and all it does is distract me | C65: Remote-First Policy
A66: 54 | C66: No Action / Not Applicable
A67: 55 | B67: Put more resources towards making infrastructure work better | C67: Infrastructure Reliability
A68: 56 | B68: Stop all irrelevant company-wide emails | C68: Email Policy
A69: 57 | C69: No Action / Not Applicable
A70: 58 | C70: No Action / Not Applicable
A71: 59 | B71: maybe more courses to systematize knowledge | C71: Training / Knowledge Development
A72: 60 | B72: Employ more technical people, who are willing to learn more | C72: Staffing & Skill Level
A73: 61 | B73: Less meetings | C73: Meeting Reduction
A74: 62 | C74: No Action / Not Applicable
A75: 63 | C75: No Action / Not Applicable
A76: 64 | B76: better planning | C76: Company Planning
A77: 65 | B77: Encourage people to use emails instead of chats | C77: Asynchronous Communication
A78: 66 | B78: No idea :-) maybe some sort of training? | C78: Training / Knowledge Development
A79: 67 | B79: More trainings | C79: Training / Knowledge Development
A80: 68 | B80: Reduce meeting overall. | C80: Meeting Reduction
A81: 69 | B81: make everyone aware of effects of disruptions | C81: Awareness & Education
A82: 69 | B82: encourage teams to have "quite zone" and "chatter zones" | C82: Zoned Office Spaces
A83: 69 | B83: inter team communication should be bounded to be scheduled (no adhoc meetings outside teams) | C83: Scheduled Cross-Team Communication
A84: 70 | C84: No Action / Not Applicable
B89: Etykiety wierszy | C89: Liczba z Survey Id
B90: No Action / Not Applicable | C90: 33
B91: Meeting Reduction | C91: 7
B92: Company Communication Guidelines | C92: 4
B93: Training / Knowledge Development | C93: 3
B94: Silent Hours / Focus Policy | C94: 2
B95: Email Policy | C95: 2
B96: Office Space for Focus | C96: 2
B97: Remote Work Policy | C97: 1
B98: Tool Usage Guidelines | C98: 1
B99: Company Planning | C99: 1
B100: Clarity of Requirements | C100: 1
B101: Workload & Prioritization | C101: 1
... B125: Process Improvement | C125: 1
B126: (puste)
B127: Suma końcowa | C127: 82

Sheet charts
A1: How frequently do you experience interruptions in a typical workday? | L1: What are the most common sources of interruptions in your work?
A2: Etykiety wierszy | B2: Liczba z Id | L2: Etykiety wierszy | M2: Liczba z Id
A3: Less than 3 times per day | B3: 14 | L3: Discussions with team members nearby | M3: 1
A4: 3–6 times | B4: 31 | L4: System failure or unplanned blockers | M4: 1
A5: 7–10 times | B5: 13 | L5: Personal issues | M5: 1
A6: More than 10 times | B6: 16 | L6: Work environment | M6: 27
A7: Suma końcowa | B7: 74 | L7: System notifications and emails | M7: 34
L8: Self-interruptions | M8: 35
L9: Meetings and quick conversations | M9: 49
L10: Team chats and messages | M10: 64
L11: Suma końcowa | M11: 212
A33: How much do interruptions disrupt your focus and workflow? (1 = not disruptive at all, 5 = very disruptive) | L33: On average, how long does it take you to regain full focus after an interruption?
A34: Etykiety wierszy | B34: Liczba z Id | L34: Etykiety wierszy | M34: Liczba z Id
A35: 1 | B35: 2 | L35: Immediately | M35: 5
A36: 2 | B36: 13 | L36: 1 - 15 minutes | M36: 33
A37: 3 | B37: 28 | L37: 15 - 30 minutes | M37: 26
A38: 4 | B38: 25 | L38: 30 - 60 minutes | M38: 8
A39: 5 | B39: 6 | L39: more than 60 minutes | M39: 2
A40: Suma końcowa | B40: 74 | L40: Suma końcowa | M40: 74
A67: How do you rate your productivity in a typical workday? (1 = very low, 5 = very high) | L67: How satisfied are you with your job overall (job satisfaction)? (1 = very dissatisfied, 5 = very satisfied)
A68: Etykiety wierszy | B68: Liczba z Id | L68: Etykiety wierszy | M68: Liczba z Id
A69: 2 | B69: 4 | L69: 1 | M69: 2
A70: 3 | B70: 23 | L70: 2 | M70: 4
A71: 4 | B71: 38 | L71: 3 | M71: 12
A72: 5 | B72: 9 | L72: 4 | M72: 39
A73: Suma końcowa | B73: 74 | L73: 5 | M73: 17
L74: Suma końcowa | M74: 74
A99: Who interrupts you most often at work? | L99: What are these interruptions usually about?
A100: Etykiety wierszy | B100: Liczba z Id | L100: Etykiety wierszy | M100: Liczba z Id
A101: Members of my teams | B101: 1 | L101: Noise unrelated to work | M101: 1
A102: family | B102: 1 | L102: Casual chats | M102: 1
A103: Most often I am the one who interrupts others by asking questions | B103: 1 | L103: Informal, non-work related | M103: 1
A104: Senior colleagues | B104: 3 | L104: Code review | M104: 14
A105: Other departments (HR, sales, marketing) | B105: 3 | L105: Task status reminders | M105: 15
A106: Client / end user | B106: 5 | L106: Implementation details | M106: 22
A107: Manager / product owner (formal supervisor or decision-maker) | B107: 9 | L107: Requests for help with environment issues | M107: 32
A108: People in supporting or junior roles (e.g., less experienced team members) | B108: 12 | L108: Notifications from communication tools | M108: 33
A109: Colleagues at the same level (team members / peers) | B109: 38 | L109: Organizational matters (e.g., meetings, planning) | M109: 45
A110: Suma końcowa | B110: 73 | L110: Technical questions or code questions | M110: 45
L111: Suma końcowa | M111: 209
A134: How quickly do you switch to handling the new "interrupting " task? | L134: What methods do you personally use to reduce or manage interruptions during your work? (max. 3)
A135: Etykiety wierszy | B135: Liczba z Id | L135: Liczba z Id | M135: Etykiety kolumn
A136: Immediately | B136: 15 | L136: Etykiety wierszy | M136: 2 | N136: 3 | O136: 4 | P136: 5 | Q136: Suma końcowa
A137: 1 - 15 minutes | B137: 47 | L137: Availability Signaling | M137: 1 | N137: 11 | O137: 5 | P137: 1 | Q137: 18
A138: 15 - 30 minutes | B138: 8 | L138: Calendar & Time Blocking | M138: 2 | N138: 5 | O138: 3 | P138: 2 | Q138: 12
A139: 30 - 60 minutes | B139: 4 | L139: Task & Priority Management | M139: 2 | O139: 3 | Q139: 5
A140: Suma końcowa | B140: 74 | L140: Noise Reduction | M140: 1 | N140: 1 | O140: 3 | Q140: 5
L141: Self-regulation & Autonomy | N141: 2 | O141: 1 | P141: 1 | Q141: 4
L142: Communication Practices | N142: 1 | O142: 2 | Q142: 3
L143: Physical / Context Isolation | N143: 1 | O143: 2 | Q143: 3
L144: Suma końcowa | M144: 6 | N144: 21 | O144: 19 | P144: 4 | Q144: 50
A182: Do you use any techniques to reduce interruptions (e.g., focus time, “do not disturb” status)? | L182: What methods do you personally use to reduce or manage interruptions during your work? (max. 3)
A183: Etykiety wierszy | B183: Liczba z Id | L183: Etykiety wierszy | M183: Liczba z Id
A184: No | B184: 40 | L184: Communication Practices | M184: 3
A185: Sometimes | B185: 14 | L185: Physical / Context Isolation | M185: 3
A186: Yes | B186: 20 | L186: Self-regulation & Autonomy | M186: 4
A187: Suma końcowa | B187: 74 | L187: Noise Reduction | M187: 5
L188: Task & Priority Management | M188: 5
L189: Calendar & Time Blocking | M189: 12
L190: Availability Signaling | M190: 18
L191: Suma końcowa | M191: 50
A210: demography | L210: What methods do you personally use to reduce or manage interruptions during your work? (max. 3)
L211: Etykiety wierszy | M211: Liczba z Id
L212: Communication Practices | M212: 3
L213: Physical / Context Isolation | M213: 3
A214: Liczba z Id | B214: Etykiety kolumn | L214: Self-regulation & Autonomy | M214: 4
A215: Etykiety wierszy | B215: 18 - 24 | C215: 25 - 29 | D215: 30 - 34 | E215: 35-44 | F215: 45 - 54 | G215: 55 - 64 | H215: Suma końcowa | L215: Noise Reduction | M215: 5
A216: Bachelor’s degree | B216: 18 | C216: 3 | D216: 2 | E216: 3 | F216: 1 | H216: 27 | L216: Task & Priority Management | M216: 5
A217: High school | B217: 9 | D217: 1 | H217: 10 | L217: Calendar & Time Blocking | M217: 12
A218: Master’s degree | B218: 4 | C218: 4 | D218: 6 | E218: 9 | F218: 5 | G218: 1 | H218: 29 | L218: Availability Signaling | M218: 18
A219: PhD | C219: 1 | D219: 1 | E219: 2 | F219: 3 | G219: 1 | H219: 8 | L219: Suma końcowa | M219: 50
A220: Suma końcowa | B220: 31 | C220: 8 | D220: 10 | E220: 14 | F220: 9 | G220: 2 | H220: 74

Sheet Work arrangements chart
A1: Work arrangement | B1: Disruptiveness | E1: Remote | F1: Hybrid | G1: On-site
A2: Hybrid | B2: 2 | E2: 4 | F2: 2 | G2: 4
A3: Hybrid | B3: 2 | E3: 4 | F3: 2 | G3: 4
A4: On-site | B4: 4 | E4: 5 | F4: 4 | G4: 4
A5: Hybrid | B5: 4 | E5: 3 | F5: 3 | G5: 3
A6: Hybrid | B6: 3 | E6: 2 | F6: 3 | G6: 3
A7: Hybrid | B7: 3 | E7: 3 | F7: 3 | G7: 4
A8: Remote | B8: 4 | E8: 5 | F8: 3 | G8: 4
A9: Remote | B9: 4 | E9: 4 | F9: 3 | G9: 4
A10: Hybrid | B10: 3 | E10: 3 | F10: 3 | G10: 4
A11: Remote | B11: 5 | E11: 5 | F11: 4 | G11: 2
A12: On-site | B12: 4 | E12: 4 | F12: 3 | G12: 3
A13: Hybrid | B13: 3 | E13: 3 | F13: 3
A14: On-site | B14: 4 | E14: 4 | F14: 3
A15: Hybrid | B15: 3 | E15: 4 | F15: 2
A16: On-site | B16: 3 | E16: 1 | F16: 3
A17: On-site | B17: 3 | E17: 5 | F17: 3
A18: Hybrid | B18: 3 | E18: 5 | F18: 4
A19: Remote | B19: 3 | E19: 2 | F19: 2
A20: On-site | B20: 4 | E20: 2 | F20: 3
A21: Hybrid | B21: 4 | E21: 4 | F21: 2
A22: Hybrid | B22: 3 | E22: 4 | F22: 2
A23: Hybrid | B23: 3 | E23: 4 | F23: 4
A24: Hybrid | B24: 3 | E24: 4 | F24: 4
... A26: On-site | B26: 4 | E26: 3 | F26: 2
A27: Remote | B27: 3 | F27: 4
A28: Hybrid | B28: 2 | F28: 2
A29: Remote | B29: 5 | F29: 2
A30: Hybrid | B30: 3 | F30: 3
A31: Remote | B31: 4 | F31: 5
A32: Remote | B32: 3 | F32: 1
A33: Hybrid | B33: 3 | F33: 4
A34: Hybrid | B34: 4 | F34: 3
A35: Hybrid | B35: 2 | F35: 3
A36: Remote | B36: 5 | F36: 3
A37: Hybrid | B37: 3 | F37: 3
A38: Hybrid | B38: 2 | F38: 3
A39: Remote | B39: 4 | F39: 3
A40: Hybrid | B40: 2
A41: Hybrid | B41: 4
A42: Remote | B42: 3
A43: Hybrid | B43: 4
A44: Remote | B44: 4
A45: On-site | B45: 4
A46: Hybrid | B46: 4
A47: Hybrid | B47: 2
A48: Hybrid | B48: 4
A49: Hybrid | B49: 2
A50: On-site | B50: 4
A51: Remote | B51: 4
... A75: Hybrid | B75: 3
